{"ok": true, "pois": [{"parent": [], "distance": [], "keytag": "风景名胜,公园广场,公园广场", "importance": [], "biz_ext": {"cost": [], "opentime2": "周一至周日 00:00-24:00", "level": [], "rating": "3.5", "open_time": "24小时营业", "ticket_ordering": "0"}, "type": "风景名胜;公园广场;公园广场", "photos": [], "building": [], "typecode": "110100", "shopinfo": "2", "poiweight": [], "adname": "东港市", "featured_reviews_remake": [], "tel": [], "id": "B0FFFA7VHW", "address": "安阳东街旁边", "space_num": [], "pname": "辽宁省", "biz_type": "tour", "cityname": "丹东市", "childtype": [], "atag": [], "name": "前阳一拐弯", "location": "124.221511,39.957764", "shopid": [], "favorite_num": [], "featured_reviews": []}, {"parent": "B019F019C1", "distance": [], "keytag": "森林公园", "importance": [], "biz_ext": {"cost": [], "opentime2": [], "level": [], "rating": "3.4", "open_time": [], "ticket_ordering": "0"}, "type": "风景名胜;风景名胜;风景名胜", "photos": [{"provider": [], "title": [], "url": "https://aos-comment.amap.com/B0JBFR078D/comment/content_media_external_images_media_1000079588_ss__1762817018078_08066387.jpg"}, {"provider": [], "title": [], "url": "https://aos-comment.amap.com/B0JBFR078D/comment/content_media_external_images_media_1000079578_ss__1762817018164_32169208.jpg"}, {"provider": [], "title": [], "url": "https://aos-comment.amap.com/B0JBFR078D/comment/31F6B458_335F_43A0_8FED_E42420B851C4_L0_001_2000_133_1765612454429_87581176.jpg"}], "building": [], "typecode": "110200", "shopinfo": "2", "poiweight": [], "adname": "振兴区", "featured_reviews_remake": [], "tel": [], "id": "B0JBFR078D", "address": "宾馆路132号", "space_num": [], "pname": "辽宁省", "biz_type": "tour", "cityname": "丹东市", "childtype": "301", "atag": [], "name": "樱花林", "location": "124.370740,40.131554", "shopid": [], "favorite_num": [], "featured_reviews": []}, {"parent": [], "distance": [], "keytag": "清真寺", "importance": [], "biz_ext": {"cost": [], "opentime2": [], "level": [], "rating": "3.5", "open_time": [], "ticket_ordering": "0"}, "type": "风景名胜;风景名胜;回教寺", "photos": [{"provider": [], "title": [], "url": "http://store.is.autonavi.com/showpic/6c6ea01d60fd22a4c5faf262b82362e9"}], "building": [], "typecode": "110207", "shopinfo": "2", "poiweight": [], "adname": "东港市", "featured_reviews_remake": [], "tel": [], "id": "B0FFH687QM", "address": "环城大街与镇北街交叉口东北340米", "space_num": [], "pname": "辽宁省", "biz_type": "tour", "cityname": "丹东市", "childtype": [], "atag": [], "name": "东港清真寺", "location": "124.144082,39.902988", "shopid": [], "favorite_num": [], "featured_reviews": []}, {"parent": [], "distance": [], "keytag": "滨江公园", "importance": [], "biz_ext": {"cost": [], "opentime2": "周一至周日 00:00-24:00", "level": [], "rating": "3.5", "open_time": "24小时营业", "ticket_ordering": "0"}, "type": "风景名胜;公园广场;公园", "photos": [{"provider": [], "title": [], "url": "https://aos-comment.amap.com/B019F02MPW/comment/content_media_external_images_media_210452_ss__1766715325159_11637823.jpg"}, {"provider": [], "title": [], "url": "http://store.is.autonavi.com/showpic/7f724e729539bb3939c8489e8928a2dd"}, {"provider": [], "title": [], "url": "http://store.is.autonavi.com/showpic/65fad76de74d5b3d9fcb36d3ae37ca32"}], "building": [], "typecode": "110101", "shopinfo": "2", "poiweight": [], "adname": "振安区", "featured_reviews_remake": [], "tel": [], "id": "B019F02MPW", "address": "滨江东路", "space_num": [], "pname": "辽宁省", "biz_type": "tour", "cityname": "丹东市", "childtype": [], "atag": [], "name": "鸭绿江文化风情园", "location": "124.417377,40.144471", "shopid": [], "favorite_num": [], "featured_reviews": []}, {"parent": "B019F00SKA", "distance": [], "keytag": "湿地", "importance": [], "biz_ext": {"cost": [], "opentime2": "周一至周日 00:00-24:00", "level": [], "rating": "4.1", "open_time": "24小时营业", "ticket_ordering": "0"}, "type": "风景名胜;风景名胜;风景名胜", "photos": [{"provider": [], "title": [], "url": "https://aos-comment.amap.com/B0FFJGIROE/comment/1660189357830_temp_1660189359800_fd9576c8.jpg"}, {"provider": [], "title": [], "url": "https://aos-comment.amap.com/B0FFJGIROE/comment/1660189390518_temp_1660189391731_675482e3.jpg"}, {"provider": [], "title": [], "url": "https://aos-comment.amap.com/B0FFJGIROE/comment/file_media_Photo_15835_IMG_1754559776_14468_IMG_20250807_174116_jpg_ss_2.jpg"}], "building": [], "typecode": "110200", "shopinfo": "2", "poiweight": [], "adname": "东港市", "featured_reviews_remake": [], "tel": [], "id": "B0FFJGIROE", "address": "五四农场五四农场滨海公路南侧", "space_num": [], "pname": "辽宁省", "biz_type": "tour", "cityname": "丹东市", "childtype": "301", "atag": [], "name": "鸭绿江湿地(暂停开放)", "location": "124.000281,39.808282", "shopid": [], "favorite_num": [], "featured_reviews": []}, {"parent": "B0FFJGIROE", "distance": [], "keytag": "自然风光", "importance": [], "biz_ext": {"cost": [], "opentime2": [], "level": [], "rating": "3.9", "open_time": [], "ticket_ordering": "0"}, "type": "风景名胜;风景名胜;海滩", "photos": [{"provider": [], "title": [], "url": "http://store.is.autonavi.com/showpic/0bac4659abc3957aeaee243acc8e0bf3"}, {"provider": [], "title": [], "url": "https://aos-comment.amap.com/B019F00SKA/comment/4eb32e96a16569935eddc47e1fc6b157_2048_2048_80.jpg"}, {"provider": [], "title": [], "url": "https://aos-comment.amap.com/B019F00SKA/comment/5051c3b898a9bdad96c45b72bbb325df_2048_2048_80.jpg"}], "building": [], "typecode": "110208", "shopinfo": "2", "poiweight": [], "adname": "东港市", "featured_reviews_remake": [], "tel": [], "id": "B019F00SKA", "address": "鸭绿江湿地", "space_num": [], "pname": "辽宁省", "biz_type": "tour", "cityname": "丹东市", "childtype": "301", "atag": [], "name": "零海岸泥螺滩", "location": "124.000276,39.808282", "shopid": [], "favorite_num": [], "featured_reviews": []}, {"parent": [], "distance": [], "keytag": "景区", "importance": [], "biz_ext": {"cost": [], "opentime2": [], "level": [], "rating": "3.8", "open_time": [], "ticket_ordering": "0"}, "type": "风景名胜;风景名胜;风景名胜", "photos": [{"provider": [], "title": [], "url": "http://store.is.autonavi.com/showpic/f93c9c43701bc24696587546d82d09ba"}, {"provider": [], "title": [], "url": "http://store.is.autonavi.com/showpic/33581b3fbaaa6334b047c3995e7b02e1"}, {"provider": [], "title": [], "url": "https://aos-comment.amap.com/B0K2MHVBTY/comment/content_media_external_images_media_21161_ss__1767676578452_00628101.jpg"}], "building": [], "typecode": "110200", "shopinfo": "2", "poiweight": [], "adname": "振兴区", "featured_reviews_remake": [], "tel": "16794156666", "id": "B0K2MHVBTY", "address": "月亮岛大街17-111号", "space_num": [], "pname": "辽宁省", "biz_type": "tour", "cityname": "丹东市", "childtype": [], "atag": [], "name": "丹东界河旅游度假区", "location": "124.368010,40.093880", "shopid": [], "favorite_num": [], "featured_reviews": []}, {"parent": [], "distance": [], "keytag": "教堂", "importance": [], "biz_ext": {"cost": [], "opentime2": [], "level": [], "rating": "3.4", "open_time": [], "ticket_ordering": "0"}, "type": "风景名胜;风景名胜;教堂", "photos": [{"provider": [], "title": [], "url": "https://store.is.autonavi.com/showpic/093895b387d53d4a9b033bbb562bc87e"}, {"provider": [], "title": [], "url": "http://store.is.autonavi.com/showpic/0745b48530cd9f604e4224554bac416e"}, {"provider": [], "title": [], "url": "https://store.is.autonavi.com/showpic/b98536f4edcc74740000000733484283"}], "building": [], "typecode": "110206", "shopinfo": "2", "poiweight": [], "adname": "元宝区", "featured_reviews_remake": [], "tel": [], "id": "B019F02SAM", "address": "天后宫街教堂路24号", "space_num": [], "pname": "辽宁省", "biz_type": "tour", "cityname": "丹东市", "childtype": [], "atag": [], "name": "元宝山基督教礼拜堂", "location": "124.398738,40.143369", "shopid": [], "favorite_num": [], "featured_reviews": []}, {"parent": [], "distance": [], "keytag": "烈士陵园", "importance": [], "biz_ext": {"cost": [], "opentime2": [], "rating": [], "open_time": []}, "type": "生活服务;丧葬设施;陵园", "photos": [{"title": [], "url": "https://store.is.autonavi.com/showpic/488c880e0f563af21e51546e59d43343"}], "building": [], "typecode": "071901", "shopinfo": "0", "poiweight": [], "adname": "振兴区", "featured_reviews_remake": [], "tel": [], "id": "B0IANUHJYO", "address": [], "space_num": [], "pname": "辽宁省", "biz_type": [], "cityname": "丹东市", "childtype": [], "atag": [], "name": "革命烈士陵园", "location": "124.314765,40.056550", "shopid": [], "favorite_num": [], "featured_reviews": []}, {"parent": [], "distance": [], "keytag": "文物古迹", "importance": [], "biz_ext": {"cost": [], "opentime2": [], "level": [], "rating": "3.9", "open_time": [], "ticket_ordering": "0"}, "type": "风景名胜;风景名胜;风景名胜", "photos": [{"provider": [], "title": [], "url": "https://store.is.autonavi.com/showpic/a3d83c920d9701f40000002904500833?type=pic"}, {"provider": [], "title": [], "url": "https://aos-comment.amap.com/B0K6T5OYPD/comment/0e2b788768cf3f61c223e079386edcc9_2048_2048_80.jpg"}, {"provider": [], "title": [], "url": "https://aos-comment.amap.com/B0K6T5OYPD/comment/eb0d3d43d17bf26905f132fa544f0db6_2048_2048_80.jpg"}], "building": [], "typecode": "110200", "shopinfo": "2", "poiweight": [], "adname": "振安区", "featured_reviews_remake": [], "tel": [], "id": "B0K6T5OYPD", "address": [], "space_num": [], "pname": "辽宁省", "biz_type": "tour", "cityname": "丹东市", "childtype": [], "atag": [], "name": "江沿台堡遗址", "location": "124.461187,40.288263", "shopid": [], "favorite_num": [], "featured_reviews": []}, {"parent": [], "distance": [], "keytag": "人文景观", "importance": [], "biz_ext": {"cost": [], "opentime2": [], "level": [], "rating": "3.9", "open_time": [], "ticket_ordering": "0"}, "type": "风景名胜;风景名胜;风景名胜", "photos": [{"provider": [], "title": [], "url": "http://store.is.autonavi.com/showpic/403ec851272824755a0428ee8ec2eb4e"}, {"provider": [], "title": [], "url": "http://store.is.autonavi.com/showpic/0d28ccd73bcf44b8cb63cfcd863f0359"}, {"provider": [], "title": [], "url": "http://store.is.autonavi.com/showpic/638b74e92001fbb7e161824a056114af"}], "building": [], "typecode": "110200", "shopinfo": "2", "poiweight": [], "adname": "振安区", "featured_reviews_remake": [], "tel": [], "id": "B0K6XHXP6V", "address": "东平大街12号", "space_num": [], "pname": "辽宁省", "biz_type": "tour", "cityname": "丹东市", "childtype": [], "atag": [], "name": "日俄战争遗址-俄国坟", "location": "124.468574,40.207836", "shopid": [], "favorite_num": [], "featured_reviews": []}, {"parent": [], "distance": [], "keytag": "博物馆", "importance": [], "biz_ext": {"cost": [], "opentime2": [], "rating": "3.4", "open_time": []}, "type": "科教文化服务;博物馆;博物馆", "photos": [{"title": [], "url": "https://store.is.autonavi.com/showpic/10e463e07a65929c7ffb534bf86dad0a"}], "building": [], "typecode": "140100", "shopinfo": "0", "poiweight": [], "adname": "振兴区", "featured_reviews_remake": [], "tel": [], "id": "B0L03ZD2Q6", "address": "高新技术产业开发区", "space_num": [], "pname": "辽宁省", "biz_type": [], "cityname": "丹东市", "childtype": [], "atag": [], "name": "中医药满药文化博物馆", "location": "124.273856,40.009130", "shopid": [], "favorite_num": [], "featured_reviews": []}, {"parent": [], "distance": [], "keytag": "文物古迹", "importance": [], "biz_ext": {"cost": [], "opentime2": [], "level": [], "rating": "3.6", "open_time": [], "ticket_ordering": "0"}, "type": "风景名胜;风景名胜;风景名胜", "photos": [{"provider": [], "title": [], "url": "https://store.is.autonavi.com/showpic/b5933f491bd863b14827efd75c2b0e40"}], "building": [], "typecode": "110200", "shopinfo": "2", "poiweight": [], "adname": "元宝区", "featured_reviews_remake": [], "tel": [], "id": "B0KUB7MP0D", "address": "滨江东路与东齐路交叉口西南400米", "space_num": [], "pname": "辽宁省", "biz_type": "tour", "cityname": "丹东市", "childtype": [], "atag": [], "name": "告别祖国雕塑", "location": "124.415903,40.142153", "shopid": [], "favorite_num": [], "featured_reviews": []}, {"parent": [], "distance": [], "keytag": "广场", "importance": [], "biz_ext": {"cost": [], "opentime2": "周一至周日 00:00-24:00", "rating": "3.1", "open_time": "24小时营业"}, "type": "体育休闲服务;休闲场所;休闲场所", "photos": [], "building": [], "typecode": "080500", "shopinfo": "0", "poiweight": [], "adname": "东港市", "featured_reviews_remake": [], "tel": [], "id": "B0L3TX8QPI", "address": "前阳镇农民村退役军人服务站东南侧80米", "space_num": [], "pname": "辽宁省", "biz_type": [], "cityname": "丹东市", "childtype": [], "atag": [], "name": "农民村文化广场", "location": "124.255252,39.974841", "shopid": [], "favorite_num": [], "featured_reviews": []}, {"parent": "B019F019C1", "distance": [], "keytag": "植物园", "importance": [], "biz_ext": {"cost": [], "opentime2": "周一至周日 00:00-24:00", "level": [], "rating": "3.7", "open_time": "24小时营业", "ticket_ordering": "0"}, "type": "风景名胜;公园广场;植物园", "photos": [{"provider": [], "title": [], "url": "https://aos-comment.amap.com/B019F0ORCL/comment/content_media_external_images_media_1000079594_ss__1765032424135_46031028.jpg"}, {"provider": [], "title": [], "url": "https://aos-comment.amap.com/B019F0ORCL/comment/C5B44FF5_EC65_4FCF_B21E_81C17341045E_L0_001_2000_133_1765612654731_04641013.jpg"}, {"provider": [], "title": [], "url": "https://aos-comment.amap.com/B019F0ORCL/comment/9CDCCE96_1704_4715_978C_FA84101F8E92_L0_001_2000_133_1765612654729_61270547.jpg"}], "building": [], "typecode": "110103", "shopinfo": "2", "poiweight": [], "adname": "振兴区", "featured_reviews_remake": [], "tel": "0415-2255896", "id": "B019F0ORCL", "address": "山上街93号锦江山公园", "space_num": [], "pname": "辽宁省", "biz_type": "tour", "cityname": "丹东市", "childtype": "301", "atag": [], "name": "丹东市植物园", "location": "124.374951,40.133780", "shopid": [], "favorite_num": [], "featured_reviews": []}, {"parent": "B0HKD73NA3", "distance": [], "keytag": "舒适型", "importance": [], "biz_ext": {"cost": [], "star": [], "opentime2": [], "rating": "4.2", "lowest_price": [], "hotel_ordering": "0", "open_time": []}, "type": "住宿服务;宾馆酒店;四星级宾馆|生活服务;洗浴推拿场所;洗浴推拿场所", "photos": [{"provider": [], "title": [], "url": "http://store.is.autonavi.com/showpic/20dfecbbcf811ed77c86a2ca3012641f"}, {"provider": [], "title": [], "url": "https://store.is.autonavi.com/showpic/f39bf2b1d00ec01d0000000588798830"}, {"provider": [], "title": [], "url": "https://aos-comment.amap.com/B019F0P4D9/comment/1687424632061_temp_1687424633693_87c27bb8.jpg"}], "building": [], "typecode": "100103|071400", "shopinfo": "0", "poiweight": [], "adname": "振安区", "featured_reviews_remake": [], "tel": "0415-2293333", "id": "B0HKD73NA3", "address": "五龙背镇站前西街26-1号", "space_num": [], "pname": "辽宁省", "biz_type": "hotel", "cityname": "丹东市", "childtype": "323", "atag": [], "name": "金海温泉", "location": "124.267227,40.260771", "shopid": [], "favorite_num": [], "featured_reviews": []}, {"parent": [], "distance": [], "keytag": "温泉", "importance": [], "biz_ext": {"cost": [], "opentime2": "周一至周日 08:00-19:00", "rating": "4.0", "open_time": "08:00-19:00"}, "type": "体育休闲服务;度假疗养场所;度假村", "photos": [{"title": [], "url": "http://store.is.autonavi.com/showpic/a9a901fedd4b5a34d76b31483837dc3c"}], "building": [], "typecode": "080401", "shopinfo": "0", "poiweight": [], "adname": "振安区", "featured_reviews_remake": [], "tel": "18242574442", "id": "B0FFG0641M", "address": "五龙背镇站后西街16-3号", "space_num": [], "pname": "辽宁省", "biz_type": [], "cityname": "丹东市", "childtype": [], "atag": [], "name": "五龙温泉会所", "location": "124.271496,40.263881", "shopid": [], "favorite_num": [], "featured_reviews": []}, {"parent": [], "distance": [], "keytag": "生活服务,生活服务场所,生活服务场所", "importance": [], "biz_ext": {"cost": [], "opentime2": [], "rating": "3.1", "open_time": []}, "type": "生活服务;生活服务场所;生活服务场所", "photos": [], "building": [], "typecode": "070000", "shopinfo": "0", "poiweight": [], "adname": "振兴区", "featured_reviews_remake": [], "tel": [], "id": "B0L3UUHMEI", "address": "滨江中路与春五路交叉口东南20米", "space_num": [], "pname": "辽宁省", "biz_type": [], "cityname": "丹东市", "childtype": [], "atag": [], "name": "鸭绿江国家级风景名胜区-吸烟区", "location": "124.365239,40.096759", "shopid": [], "favorite_num": [], "featured_reviews": []}, {"parent": [], "distance": [], "keytag": "纪念馆", "importance": [], "biz_ext": {"cost": [], "opentime2": [], "level": [], "rating": "3.8", "open_time": [], "ticket_ordering": "0"}, "type": "风景名胜;风景名胜;纪念馆", "photos": [{"provider": [], "title": [], "url": "http://store.is.autonavi.com/showpic/f275daa1c8f33c4b0662875cb818fb0b"}, {"provider": [], "title": [], "url": "http://store.is.autonavi.com/showpic/323bd919f8cbe952d9458c026a3fc037"}, {"provider": [], "title": [], "url": "http://store.is.autonavi.com/showpic/f50ca40b2a2deec534cdd6e5e7dac940"}], "building": [], "typecode": "110204", "shopinfo": "2", "poiweight": [], "adname": "东港市", "featured_reviews_remake": [], "tel": [], "id": "B0FFL2BYSA", "address": "南岗头", "space_num": [], "pname": "辽宁省", "biz_type": "tour", "cityname": "丹东市", "childtype": [], "atag": [], "name": "南岗头惨案纪念馆", "location": "124.032265,39.997977", "shopid": [], "favorite_num": [], "featured_reviews": []}, {"parent": [], "distance": [], "keytag": "湖泊河流", "importance": [], "biz_ext": {"cost": [], "opentime2": "周一至周日 08:00-18:00", "level": [], "rating": "4.0", "open_time": "08:00-18:00", "ticket_ordering": "0"}, "type": "风景名胜;风景名胜相关;旅游景点", "photos": [{"provider": [], "title": [], "url": "https://store.is.autonavi.com/showpic/009302d9ff01bb91553ee0444fa289ee"}, {"provider": [], "title": [], "url": "https://aos-comment.amap.com/B019F00XFR/comment/27B3CD8A_1915_42F0_8623_1540D73F3649_L0_001_1512_201_1765372071264_81271962.jpg"}, {"provider": [], "title": [], "url": "https://aos-comment.amap.com/B019F00XFR/comment/975BE9C3_6768_49BE_A543_942DDCA7ECB8_L0_001_2000_93_1765369383856_34870733.jpg"}], "building": [], "typecode": "110000", "shopinfo": "2", "poiweight": [], "adname": "凤城市", "featured_reviews_remake": [], "tel": [], "id": "B019F00XFR", "address": "玉龙湖开发区", "space_num": [], "pname": "辽宁省", "biz_type": "tour", "cityname": "丹东市", "childtype": [], "atag": [], "name": "玉龙湖景区", "location": "123.914582,40.168467", "shopid": [], "favorite_num": [], "featured_reviews": []}, {"parent": [], "distance": [], "keytag": "风景名胜,风景名胜相关,旅游景点", "importance": [], "biz_ext": {"cost": [], "opentime2": [], "level": [], "rating": "3.5", "open_time": [], "ticket_ordering": "0"}, "type": "风景名胜;风景名胜相关;旅游景点", "photos": [{"provider": [], "title": [], "url": "https://store.is.autonavi.com/showpic/b20cd8f3fb0d7e0f393bcd593fa5e8fb"}, {"provider": [], "title": [], "url": "https://store.is.autonavi.com/showpic/31147915d9d4720afd7b8d952a6359b7"}, {"provider": [], "title": [], "url": "https://store.is.autonavi.com/showpic/b3e5b138c4adac6795ce20637f86e012"}], "building": [], "typecode": "110000", "shopinfo": "2", "poiweight": [], "adname": "东港市", "featured_reviews_remake": [], "tel": [], "id": "B0L29GQTTU", "address": "孙家堡子附近", "space_num": [], "pname": "辽宁省", "biz_type": "tour", "cityname": "丹东市", "childtype": [], "atag": [], "name": "长清湖-枕水居", "location": "124.014974,40.100386", "shopid": [], "favorite_num": [], "featured_reviews": []}, {"parent": [], "distance": [], "keytag": "滑雪", "importance": [], "biz_ext": {"cost": [], "opentime2": "12/20-12/31 08:30-16:00开放；1/1-2/26 08:30-16:00开放； 说明:具体营业状态以当天开放情况为准。", "rating": "4.4", "open_time": "08:30-16:00 08:30-16:00"}, "type": "体育休闲服务;运动场馆;滑雪场", "photos": [{"title": [], "url": "http://store.is.autonavi.com/showpic/6c6b47f00d388c1e85a47b28f903539f"}, {"title": [], "url": "https://aos-comment.amap.com/B019F018P6/comment/e56ad25f4d7c70dab352e96cb65c9512_2048_2048_80.jpg"}, {"title": [], "url": "https://aos-comment.amap.com/B019F018P6/comment/file_media_Photo_10892_IMG_1770876368_10840_IMG_20260212_140428_jpg_ss__1771648678769_54646162.jpg"}], "building": [], "typecode": "080106", "shopinfo": "0", "poiweight": [], "adname": "振安区", "featured_reviews_remake": [], "tel": "13234250912", "id": "B019F018P6", "address": "楼房镇梨树村五龙高尔夫俱乐部内", "space_num": [], "pname": "辽宁省", "biz_type": [], "cityname": "丹东市", "childtype": [], "atag": [], "name": "丹东五龙高尔夫滑雪场(暂停营业)", "location": "124.356421,40.300314", "shopid": [], "favorite_num": [], "featured_reviews": []}, {"parent": "B019F02R34", "distance": [], "keytag": "人文景观", "importance": [], "biz_ext": {"cost": [], "opentime2": [], "level": [], "rating": "3.1", "open_time": [], "ticket_ordering": "0"}, "type": "风景名胜;风景名胜相关;旅游景点", "photos": [{"provider": [], "title": [], "url": "https://store.is.autonavi.com/showpic/2c6e5211e250a00d0000002442472081?type=pic"}, {"provider": [], "title": [], "url": "https://store.is.autonavi.com/showpic/b8214eea9b633f340000002442456323?type=pic"}, {"provider": [], "title": [], "url": "https://store.is.autonavi.com/showpic/edc927908719a3ba0000002442440360?type=pic"}], "building": [], "typecode": "110000", "shopinfo": "2", "poiweight": [], "adname": "振兴区", "featured_reviews_remake": [], "tel": [], "id": "B0LKV75IJM", "address": "山上街7号抗美援朝纪念馆", "space_num": [], "pname": "辽宁省", "biz_type": "tour", "cityname": "丹东市", "childtype": "301", "atag": [], "name": "抗美援朝纪念馆-序厅", "location": "124.365613,40.118898", "shopid": [], "favorite_num": [], "featured_reviews": []}, {"parent": [], "distance": [], "keytag": "4A景区", "importance": [], "biz_ext": {"cost": [], "opentime2": "4月至10月 周一至周日 07:30-16:30；园内项目营业时间以景区公布为准", "level": "AAAA", "rating": "4.7", "open_time": [], "ticket_ordering": "0"}, "type": "风景名胜;风景名胜;国家级景点", "photos": [{"provider": [], "title": "凤凰山国家重点风景名胜区", "url": "http://store.is.autonavi.com/showpic/c1fdc4f3a34a538ae48bf52acad609f1"}, {"provider": [], "title": [], "url": "http://store.is.autonavi.com/showpic/8310adfa02a5c87283175b427b94eeec"}, {"provider": [], "title": [], "url": "http://store.is.autonavi.com/showpic/9682de59c354730931f6ff3af351007d"}], "building": [], "typecode": "110202", "shopinfo": "2", "poiweight": [], "adname": "凤城市", "featured_reviews_remake": [], "tel": "0415-8126042;0415-8126043", "id": "B019F00SJX", "address": "凤山经济管理区凤凰大道与凤山路交汇处", "space_num": [], "pname": "辽宁省", "biz_type": "tour", "cityname": "丹东市", "childtype": [], "atag": [], "name": "凤凰山", "location": "124.075347,40.415456", "shopid": [], "favorite_num": [], "featured_reviews": []}, {"parent": [], "distance": [], "keytag": "古建筑", "importance": [], "biz_ext": {"cost": [], "opentime2": [], "level": [], "rating": "3.5", "open_time": [], "ticket_ordering": "0"}, "type": "风景名胜;风景名胜相关;旅游景点", "photos": [{"provider": [], "title": [], "url": "https://aos-comment.amap.com/B0IRLHGMP8/comment/5d903178684dc10eb52b242827fab438_2048_2048_80.jpg"}, {"provider": [], "title": [], "url": "https://aos-comment.amap.com/B0IRLHGMP8/comment/5a45d0c651920cbc68d1111fcb67673a_2048_2048_80.jpg"}, {"provider": [], "title": [], "url": "https://aos-comment.amap.com/B0IRLHGMP8/comment/0dd18c6177c06e0fdecdb24ffcb0e7e8_2048_2048_80.jpg"}], "building": [], "typecode": "110000", "shopinfo": "2", "poiweight": [], "adname": "元宝区", "featured_reviews_remake": [], "tel": [], "id": "B0IRLHGMP8", "address": "草莓沟街22-7号", "space_num": [], "pname": "辽宁省", "biz_type": "tour", "cityname": "丹东市", "childtype": [], "atag": [], "name": "三泰阁", "location": "124.361819,40.153708", "shopid": [], "favorite_num": [], "featured_reviews": []}], "total": 600}