{"ok": true, "pois": [{"parent": [], "distance": [], "keytag": "教堂", "importance": [], "biz_ext": {"cost": [], "opentime2": "周日 19:00-09:00", "level": [], "rating": "4.3", "open_time": [], "ticket_ordering": "0"}, "type": "风景名胜;风景名胜;教堂", "photos": [{"provider": [], "title": [], "url": "https://store.is.autonavi.com/showpic/d2acef0994b42c851ab2a5b81ea2522b"}, {"provider": [], "title": [], "url": "https://aos-comment.amap.com/B01C304YZL/comment/C9ABD190_A4C4_48F7_A897_3754F1D7D353_L0_001_IMG_293_1763537159129_31560702.jpg"}, {"provider": [], "title": [], "url": "https://store.is.autonavi.com/showpic/3d4482c211bf0cd60000001312906048?type=pic"}], "building": [], "typecode": "110206", "shopinfo": "2", "poiweight": [], "adname": "道里区", "featured_reviews_remake": [], "tel": [], "id": "B01C304YZL", "address": "建国街210号", "space_num": [], "pname": "黑龙江省", "biz_type": "tour", "cityname": "哈尔滨市", "childtype": [], "atag": [], "name": "伯特利教堂", "location": "126.599611,45.746735", "shopid": [], "favorite_num": [], "featured_reviews": []}, {"parent": [], "distance": [], "keytag": "广场", "importance": [], "biz_ext": {"cost": [], "opentime2": "周一至周日 00:00-24:00", "level": [], "rating": "4.5", "open_time": "24小时营业", "ticket_ordering": "0"}, "type": "风景名胜;公园广场;城市广场", "photos": [{"provider": [], "title": [], "url": "https://aos-comment.amap.com/B01C302994/comment/7FB1C665_32CA_497A_BFDD_21918BCA5955_L0_001_1320_92_1765608920682_32184855.jpg"}, {"provider": [], "title": [], "url": "https://aos-comment.amap.com/B01C302994/comment/86898AB9_CCF1_4B98_912E_20080351B423_L0_001_1440_177_1770281376786_20290761.jpg"}, {"provider": [], "title": [], "url": "https://aos-comment.amap.com/B01C302994/comment/content_media_external_file_1000012340_ss__1768442905357_61630922.jpg"}], "building": [], "typecode": "110105", "shopinfo": "2", "poiweight": [], "adname": "香坊区", "featured_reviews_remake": [], "tel": [], "id": "B01C302994", "address": "进乡街23号", "space_num": [], "pname": "黑龙江省", "biz_type": "tour", "cityname": "哈尔滨市", "childtype": [], "atag": [], "name": "母亲广场", "location": "126.676921,45.710585", "shopid": [], "favorite_num": [], "featured_reviews": []}, {"parent": "B01C30J40L", "distance": [], "keytag": "红色景点", "importance": [], "biz_ext": {"cost": [], "opentime2": "1/1-12/31 周一 全天不开放；1/1-12/31 周二-周日 09:00-17:00开放；元旦节,春节,清明节,劳动节,端午节,中秋节,国庆节 09:00-17:00开放；周一闭馆(节假日除外)。", "level": [], "rating": "4.4", "open_time": [], "ticket_ordering": "0"}, "type": "风景名胜;风景名胜;红色景区|科教文化服务;展览馆;展览馆", "photos": [{"provider": [], "title": [], "url": "https://aos-comment.amap.com/B0FFG2DWSV/comment/content_media_external_images_media_147036_ss__1741156456870_84253415.jpg"}, {"provider": [], "title": [], "url": "https://store.is.autonavi.com/showpic/de20d98d2410647216b674adc6d16ba3"}, {"provider": [], "title": [], "url": "https://store.is.autonavi.com/showpic/551707c5e4c9e6b5b1fbb96e8e31d0a4"}], "building": [], "typecode": "110210|140200", "shopinfo": "2", "poiweight": [], "adname": "平房区", "featured_reviews_remake": [], "tel": "0451-51685222;0451-51747773", "id": "B0FFG2DWSV", "address": "新疆大街23号(地铁1号线新疆大街站2号口出站)", "space_num": [], "pname": "黑龙江省", "biz_type": "tour", "cityname": "哈尔滨市", "childtype": "301", "atag": [], "name": "侵华日军第七三一部队罪证陈列馆", "location": "126.639431,45.608868", "shopid": [], "favorite_num": [], "featured_reviews": []}, {"parent": [], "distance": [], "keytag": "公园", "importance": [], "biz_ext": {"cost": [], "opentime2": "周一至周日 00:00-24:00", "level": [], "rating": "4.3", "open_time": "24小时营业", "ticket_ordering": "0"}, "type": "风景名胜;公园广场;城市广场", "photos": [{"provider": [], "title": [], "url": "https://aos-comment.amap.com/B0G3N9OTSE/comment/bfecca615fc33309ae5fbdf696407e09_2048_2048_80.jpg"}, {"provider": [], "title": [], "url": "https://aos-comment.amap.com/B0G3N9OTSE/comment/cd4b723b936808627b37b4b29aec9e1b_2048_2048_80.jpg"}, {"provider": [], "title": [], "url": "https://aos-comment.amap.com/B0G3N9OTSE/comment/22b934cdecfdc842551c2e131900ffbc_2048_2048_80.jpg"}], "building": [], "typecode": "110105", "shopinfo": "2", "poiweight": [], "adname": "香坊区", "featured_reviews_remake": [], "tel": "0451-58692275", "id": "B0G3N9OTSE", "address": "前卫大街辅路与哈平路交叉口东北160米", "space_num": [], "pname": "黑龙江省", "biz_type": "tour", "cityname": "哈尔滨市", "childtype": [], "atag": [], "name": "香林园", "location": "126.650915,45.669793", "shopid": [], "favorite_num": [], "featured_reviews": []}, {"parent": [], "distance": [], "keytag": "风景名胜,风景名胜,风景名胜", "importance": [], "biz_ext": {"cost": [], "opentime2": [], "level": [], "rating": "4.1", "open_time": [], "ticket_ordering": "0"}, "type": "风景名胜;风景名胜;风景名胜", "photos": [{"provider": [], "title": [], "url": "https://store.is.autonavi.com/showpic/c7cc6bbaf91671310000002287284384?type=pic"}, {"provider": [], "title": [], "url": "https://store.is.autonavi.com/showpic/2f45b706fc4d288c0000002507746932?type=pic"}, {"provider": [], "title": [], "url": "https://store.is.autonavi.com/showpic/6a2abff33aa4f9700000002409284633?type=pic"}], "building": [], "typecode": "110200", "shopinfo": "2", "poiweight": [], "adname": "南岗区", "featured_reviews_remake": [], "tel": [], "id": "B0LA27ONZ2", "address": "郑和路与世昌路交叉口西60米", "space_num": [], "pname": "黑龙江省", "biz_type": "tour", "cityname": "哈尔滨市", "childtype": [], "atag": [], "name": "哈尔滨工程大学杏花长廊", "location": "126.682972,45.773176", "shopid": [], "favorite_num": [], "featured_reviews": []}, {"parent": "B0FFIAN47E", "distance": [], "keytag": "教堂", "importance": [], "biz_ext": {"cost": [], "opentime2": "周一至周日 00:00-24:00", "level": [], "rating": "4.5", "open_time": "24小时营业", "ticket_ordering": "0"}, "type": "风景名胜;风景名胜;教堂|生活服务;生活服务场所;生活服务场所", "photos": [{"provider": [], "title": [], "url": "https://store.is.autonavi.com/showpic/46c060789be1c83745cf1c31f034f051"}, {"provider": [], "title": [], "url": "https://store.is.autonavi.com/showpic/02b1ba882b0e89397b4f49893eebc9b5"}, {"provider": [], "title": [], "url": "https://aos-comment.amap.com/B0FFFYU3D7/comment/FE9F78F4_28E2_46BB_A03F_544EBA731CDF_L0_001_1500_200_1748432670694_94657011.jpg"}], "building": [], "typecode": "110206|070000", "shopinfo": "2", "poiweight": [], "adname": "南岗区", "featured_reviews_remake": [], "tel": [], "id": "B0FFFYU3D7", "address": "哈尔滨站北广场(东北角)", "space_num": [], "pname": "黑龙江省", "biz_type": "tour", "cityname": "哈尔滨市", "childtype": "301", "atag": [], "name": "圣·伊维尔教堂", "location": "126.629956,45.763385", "shopid": [], "favorite_num": [], "featured_reviews": []}, {"parent": "B0FFHKL3IM", "distance": [], "keytag": "风景名胜,风景名胜相关,旅游景点", "importance": [], "biz_ext": {"cost": [], "opentime2": "周一至周日 10:00-19:00", "level": [], "rating": "4.6", "open_time": "10:00-19:00", "ticket_ordering": "0"}, "type": "风景名胜;风景名胜相关;旅游景点", "photos": [{"provider": [], "title": [], "url": "https://aos-comment.amap.com/B0FFK638I0/comment/%5B2026-01-27-08-09-41%5D6AA3AB47-33C6-467F-8EE5-84854CC5B56_1769472597695_25399066.jpg"}, {"provider": [], "title": [], "url": "https://aos-comment.amap.com/B0FFK638I0/comment/785a9ba53c1fc49481620fa34d9ff970_2048_2048_80.jpg"}, {"provider": [], "title": [], "url": "https://aos-comment.amap.com/B0FFK638I0/comment/5ACFD00C_3211_4A3B_AD9D_DFBD185A8B53_L0_001_1180_152_1768892960968_63940162.jpg"}], "building": [], "typecode": "110000", "shopinfo": "2", "poiweight": [], "adname": "道外区", "featured_reviews_remake": [], "tel": [], "id": "B0FFK638I0", "address": "斯大林街2-1号火车主题广场(西南角)", "space_num": [], "pname": "黑龙江省", "biz_type": "tour", "cityname": "哈尔滨市", "childtype": "301", "atag": [], "name": "火车主题广场-中东铁路印象馆", "location": "126.627015,45.782395", "shopid": [], "favorite_num": [], "featured_reviews": []}, {"parent": "B01C30003A", "distance": [], "keytag": "植物园", "importance": [], "biz_ext": {"cost": [], "opentime2": "周一至周日 09:00-17:00", "level": [], "rating": "4.1", "open_time": "09:00-17:00", "ticket_ordering": "0"}, "type": "风景名胜;风景名胜;风景名胜", "photos": [{"provider": [], "title": [], "url": "http://store.is.autonavi.com/showpic/9372d59ac207fbe1d85f942311a63a84"}, {"provider": [], "title": [], "url": "https://store.is.autonavi.com/showpic/a2697562bcb17b440000002627470497?type=pic"}, {"provider": [], "title": [], "url": "http://store.is.autonavi.com/showpic/8d28282c0eebf1b19a130b872d915a86"}], "building": [], "typecode": "110200", "shopinfo": "2", "poiweight": [], "adname": "松北区", "featured_reviews_remake": [], "tel": [], "id": "B0I2ASMIEL", "address": "西林街13号", "space_num": [], "pname": "黑龙江省", "biz_type": "tour", "cityname": "哈尔滨市", "childtype": "301", "atag": [], "name": "哈尔滨太阳岛花卉园", "location": "126.593432,45.788665", "shopid": [], "favorite_num": [], "featured_reviews": []}, {"parent": [], "distance": [], "keytag": "烈士陵园", "importance": [], "biz_ext": {"cost": [], "opentime2": "周一关闭 (法定节假日除外)；周二至周日 08:30-11:30；13:30-16:30", "level": [], "rating": "4.6", "open_time": "08:30-11:30 13:30-16:30", "ticket_ordering": "0"}, "type": "生活服务;丧葬设施;陵园|风景名胜;风景名胜;红色景区", "photos": [{"provider": [], "title": [], "url": "https://aos-comment.amap.com/B01C304FJI/headerImg/18cdf2b469f7697be31d6fe47340f663_2048_2048_80.jpg"}, {"provider": [], "title": [], "url": "https://store.is.autonavi.com/showpic/da189a22b47714840000001916282401?type=pic"}, {"provider": [], "title": [], "url": "https://aos-comment.amap.com/B01C304FJI/headerImg/27a622e49afcbc8632790e4bbc4f62a7_2048_2048_80.jpg"}], "building": [], "typecode": "071901|110210", "shopinfo": "2", "poiweight": [], "adname": "香坊区", "featured_reviews_remake": [], "tel": "0451-82114763;0451-86267308", "id": "B01C304FJI", "address": "体育街1号(近中医学院)", "space_num": [], "pname": "黑龙江省", "biz_type": [], "cityname": "哈尔滨市", "childtype": [], "atag": [], "name": "哈尔滨烈士陵园", "location": "126.654731,45.723833", "shopid": [], "favorite_num": [], "featured_reviews": []}, {"parent": [], "distance": [], "keytag": "广场", "importance": [], "biz_ext": {"cost": [], "opentime2": "周一至周日 00:00-24:00", "level": [], "rating": "4.0", "open_time": "24小时营业", "ticket_ordering": "0"}, "type": "风景名胜;公园广场;城市广场", "photos": [{"provider": [], "title": [], "url": "https://aos-comment.amap.com/B0FFM93LGE/comment/content_media_external_file_135178_ss__1769665103351_31982866.jpg"}, {"provider": [], "title": [], "url": "https://aos-comment.amap.com/B0FFM93LGE/comment/BA4DFD7A_4A7E_4ECA_B04F_6F34C3736D15_L0_001_1500_200_1769573736672_55038443.jpg"}, {"provider": [], "title": [], "url": "https://aos-comment.amap.com/B0FFM93LGE/comment/file_media_Photo_5094_IMG_1770178678_5129_IMG_20260204_121618_jpg_ss__1770712320410_91328106.jpg"}], "building": [], "typecode": "110105", "shopinfo": "2", "poiweight": [], "adname": "松北区", "featured_reviews_remake": [], "tel": [], "id": "B0FFM93LGE", "address": "雪花南三路与创新二路交叉口东120米", "space_num": [], "pname": "黑龙江省", "biz_type": "tour", "cityname": "哈尔滨市", "childtype": [], "atag": [], "name": "雪花广场", "location": "126.507149,45.796314", "shopid": [], "favorite_num": [], "featured_reviews": []}, {"parent": [], "distance": [], "keytag": "游乐园", "importance": [], "biz_ext": {"cost": [], "opentime2": "01/26-03/31 10:00-17:00开放； 说明:恢复时间另行通知。", "rating": "4.4", "open_time": "10:00-17:00"}, "type": "体育休闲服务;体育休闲服务场所;体育休闲服务场所", "photos": [{"title": [], "url": "https://aos-comment.amap.com/B0KK27671X/comment/content_media_external_file_104566_ss__1769698283474_11322146.jpg"}, {"title": [], "url": "https://aos-comment.amap.com/B0KK27671X/comment/content_media_external_file_152493_ss__1770451222718_65215196.jpg"}, {"title": [], "url": "https://aos-comment.amap.com/B0KK27671X/comment/content_media_external_file_152477_ss__1770451222721_02744393.jpg"}], "building": [], "typecode": "080000", "shopinfo": "0", "poiweight": [], "adname": "道里区", "featured_reviews_remake": [], "tel": [], "id": "B0KK27671X", "address": "友谊西路2950号", "space_num": [], "pname": "黑龙江省", "biz_type": [], "cityname": "哈尔滨市", "childtype": [], "atag": [], "name": "大雪人奇遇乐园(暂停营业)", "location": "126.558850,45.750214", "shopid": [], "favorite_num": [], "featured_reviews": []}, {"parent": [], "distance": [], "keytag": "寺庙", "importance": [], "biz_ext": {"cost": [], "opentime2": "周一至周日 08:00-15:00", "level": [], "rating": "4.3", "open_time": "08:00-15:00", "ticket_ordering": "0"}, "type": "风景名胜;风景名胜;寺庙道观", "photos": [{"provider": [], "title": [], "url": "https://store.is.autonavi.com/showpic/ef5480a046151f1d0000000767900274?type=pic"}, {"provider": [], "title": [], "url": "http://store.is.autonavi.com/showpic/831451deaf02ec204b505f24015237ee"}, {"provider": [], "title": [], "url": "https://aos-comment.amap.com/default_poi/comment/9280AF40_5027_4D00_96C0_E5A6FE1DA7C2_L0_001_1500_200_1765348572849_55298102.jpg"}], "building": [], "typecode": "110205", "shopinfo": "2", "poiweight": [], "adname": "南岗区", "featured_reviews_remake": [], "tel": "0451-82522635", "id": "B01C3028A7", "address": "东大直街3号(工程大学地铁站2号口步行490米)", "space_num": [], "pname": "黑龙江省", "biz_type": "tour", "cityname": "哈尔滨市", "childtype": [], "atag": [], "name": "普照寺", "location": "126.666578,45.779128", "shopid": [], "favorite_num": [], "featured_reviews": []}, {"parent": [], "distance": [], "keytag": "湿地公园", "importance": [], "biz_ext": {"cost": [], "opentime2": "周一至周日 08:00-17:00", "level": [], "rating": "4.4", "open_time": "08:00-17:00", "ticket_ordering": "0"}, "type": "风景名胜;风景名胜相关;旅游景点", "photos": [{"provider": [], "title": "滨江湿地", "url": "http://store.is.autonavi.com/showpic/41a0d94de8b4d2266bdc1f36bec65f4b"}, {"provider": [], "title": [], "url": "http://store.is.autonavi.com/showpic/06e40a2f1d85ff7c24d8c90ff209da2a"}, {"provider": [], "title": [], "url": "http://store.is.autonavi.com/showpic/8ac00040638a964a4ee0b36b4f39ddea"}], "building": [], "typecode": "110000", "shopinfo": "2", "poiweight": [], "adname": "道外区", "featured_reviews_remake": [], "tel": [], "id": "B01C31B4O9", "address": "小七队屯", "space_num": [], "pname": "黑龙江省", "biz_type": "tour", "cityname": "哈尔滨市", "childtype": [], "atag": [], "name": "滨江湿地旅游风景区", "location": "126.786348,45.885044", "shopid": [], "favorite_num": [], "featured_reviews": []}, {"parent": [], "distance": [], "keytag": "广场", "importance": [], "biz_ext": {"cost": [], "opentime2": "周一至周日 00:00-24:00", "level": [], "rating": "4.3", "open_time": "24小时营业", "ticket_ordering": "0"}, "type": "风景名胜;公园广场;城市广场", "photos": [{"provider": [], "title": [], "url": "https://aos-comment.amap.com/B01C30KD44/comment/content_media_external_file_1000027682_ss__1757811072825_83256683.jpg"}, {"provider": [], "title": [], "url": "https://aos-comment.amap.com/B01C30KD44/comment/D778FD9A_340B_46C5_9F02_CA99FFAA1045_L0_001_2016_151_1763373241807_44920813.jpg"}, {"provider": [], "title": [], "url": "https://aos-comment.amap.com/B01C30KD44/comment/CAC26559_7A2A_4618_B610_6896325A912C_L0_001_2016_151_1763373241805_02086675.jpg"}], "building": [], "typecode": "110105", "shopinfo": "2", "poiweight": [], "adname": "南岗区", "featured_reviews_remake": [], "tel": [], "id": "B01C30KD44", "address": "果戈里大街与革新街交叉口南100米", "space_num": [], "pname": "黑龙江省", "biz_type": "tour", "cityname": "哈尔滨市", "childtype": [], "atag": [], "name": "激情广场", "location": "126.659576,45.751499", "shopid": [], "favorite_num": [], "featured_reviews": []}, {"parent": [], "distance": [], "keytag": "美术馆", "importance": [], "biz_ext": {"cost": [], "opentime2": "周二至周日 09:00-16:00；周一 全天关闭", "rating": "4.7", "open_time": "09:00-16:00"}, "type": "科教文化服务;科教文化场所;科教文化场所", "photos": [{"title": [], "url": "http://store.is.autonavi.com/showpic/2a278917061f469d50e165fe8f0c92ac"}, {"title": [], "url": "http://store.is.autonavi.com/showpic/3ba9feadf10681edee6fc1fac5eba387"}, {"title": [], "url": "http://store.is.autonavi.com/showpic/962c5b784ed76cd3a45b530b7fc26e7f"}], "building": [], "typecode": "140000", "shopinfo": "0", "poiweight": [], "adname": "道里区", "featured_reviews_remake": [], "tel": "0451-51870300", "id": "B0L15U0YEN", "address": "群力大道7号", "space_num": [], "pname": "黑龙江省", "biz_type": [], "cityname": "哈尔滨市", "childtype": [], "atag": [], "name": "哈尔滨美术馆", "location": "126.558664,45.740681", "shopid": [], "favorite_num": [], "featured_reviews": []}, {"parent": "B0FFGERXES", "distance": [], "keytag": "天主教堂", "importance": [], "biz_ext": {"cost": [], "opentime2": [], "seat_ordering": "0", "rating": "4.6", "open_time": []}, "type": "体育休闲服务;影剧院;剧场", "photos": [{"title": [], "url": "https://aos-comment.amap.com/B0FFH2TVQA/comment/4C81A6A7_5095_435C_9DCA_136CA34F2872_L0_001_1500_200_1766635560053_91440133.jpg"}, {"title": [], "url": "https://aos-comment.amap.com/B0FFH2TVQA/comment/content_media_external_file_12075_1767013215363_99083677.jpg"}, {"title": [], "url": "https://aos-comment.amap.com/B0FFH2TVQA/comment/176974877612_1769748778429_55816852.jpg"}], "building": [], "typecode": "080603", "shopinfo": "0", "poiweight": [], "adname": "南岗区", "featured_reviews_remake": [], "tel": [], "id": "B0FFH2TVQA", "address": "士课街47号激情广场-哈尔滨天主教堂(东北角)", "space_num": [], "pname": "黑龙江省", "biz_type": [], "cityname": "哈尔滨市", "childtype": "302", "atag": [], "name": "革新教堂大舞台", "location": "126.659547,45.751264", "shopid": [], "favorite_num": [], "featured_reviews": []}, {"parent": [], "distance": [], "keytag": "湿地", "importance": [], "biz_ext": {"cost": [], "opentime2": [], "level": [], "rating": "4.2", "open_time": [], "ticket_ordering": "0"}, "type": "风景名胜;风景名胜;风景名胜", "photos": [{"provider": [], "title": [], "url": "https://aos-comment.amap.com/comment/content_service__1772059348164_06533736_1772059389319_69798612.jpg"}, {"provider": [], "title": [], "url": "https://aos-comment.amap.com/B0LGZRWN1O/comment/F7B975F4_E86C_49AA_8581_C91C9DA156A7_L0_001_2000_116_1768417732289_04427753.jpg"}, {"provider": [], "title": [], "url": "https://aos-comment.amap.com/B0LGZRWN1O/comment/21CF5729_074D_4064_BF1A_EBC3DCC056E3_L0_001_1170_187_1759936318970_88038855.jpg"}], "building": [], "typecode": "110200", "shopinfo": "2", "poiweight": [], "adname": "松北区", "featured_reviews_remake": [], "tel": [], "id": "B0LGZRWN1O", "address": "滨水大道东40米", "space_num": [], "pname": "黑龙江省", "biz_type": "tour", "cityname": "哈尔滨市", "childtype": [], "atag": [], "name": "野鸭湾", "location": "126.694586,45.840765", "shopid": [], "favorite_num": [], "featured_reviews": []}, {"parent": [], "distance": [], "keytag": "文物古迹", "importance": [], "biz_ext": {"cost": [], "opentime2": "周一至周日 00:00-24:00", "level": [], "rating": "3.9", "open_time": "24小时营业", "ticket_ordering": "0"}, "type": "风景名胜;公园广场;公园", "photos": [{"provider": [], "title": [], "url": "https://aos-comment.amap.com/B01C30KFSV/comment/63e9d1b0cf7e64f0bb6eaf4b126ed449_2048_2048_80.jpg"}, {"provider": [], "title": [], "url": "http://aos-cdn-image.amap.com/sns/ugccomment/eff21d70-4faf-4a64-8841-b880396522e9.jpg"}, {"provider": [], "title": [], "url": "https://aos-comment.amap.com/B01C30KFSV/comment/175688689696_1756886905829_13459807.jpg"}], "building": [], "typecode": "110101", "shopinfo": "2", "poiweight": [], "adname": "道外区", "featured_reviews_remake": [], "tel": "13946013674", "id": "B01C30KFSV", "address": "北新街65号", "space_num": [], "pname": "黑龙江省", "biz_type": "tour", "cityname": "哈尔滨市", "childtype": [], "atag": [], "name": "哈尔滨市关道遗址文化公园(不对外开放)", "location": "126.657357,45.793915", "shopid": [], "favorite_num": [], "featured_reviews": []}, {"parent": [], "distance": [], "keytag": "自然风光", "importance": [], "biz_ext": {"cost": [], "opentime2": [], "level": [], "rating": "4.1", "open_time": [], "ticket_ordering": "0"}, "type": "风景名胜;风景名胜;风景名胜", "photos": [{"provider": [], "title": [], "url": "https://comment-oss-online.oss-cn-wulanchabu.aliyuncs.com/B0FFHEE18W/headerImg/2AC238E0_19F3_4A4B_9F5A_577214D8F81B_L0_001_IMG_2442_1652821155542_18231c28.HEIC"}, {"provider": [], "title": [], "url": "https://store.is.autonavi.com/showpic/5ef023328ffce4180000000668486762?type=pic"}, {"provider": [], "title": [], "url": "https://aos-comment.amap.com/B0FFHEE18W/comment/e2351e5dce4f45b1eb47e923e613eb76_2048_2048_80.jpg"}], "building": [], "typecode": "110200", "shopinfo": "2", "poiweight": [], "adname": "松北区", "featured_reviews_remake": [], "tel": [], "id": "B0FFHEE18W", "address": "松北街道松北街道滨水大道", "space_num": [], "pname": "黑龙江省", "biz_type": "tour", "cityname": "哈尔滨市", "childtype": [], "atag": [], "name": "太阳岛花田", "location": "126.561820,45.801547", "shopid": [], "favorite_num": [], "featured_reviews": []}, {"parent": [], "distance": [], "keytag": "水上乐园", "importance": [], "biz_ext": {"cost": [], "opentime2": "周一至周日 09:00-17:00 最晚进入15:30", "rating": "4.6", "open_time": "09:00-17:00"}, "type": "体育休闲服务;体育休闲服务场所;体育休闲服务场所", "photos": [{"title": [], "url": "http://store.is.autonavi.com/showpic/31798727a71c9873018905d6b9201527"}, {"title": [], "url": "https://aos-comment.amap.com/comment/content_service__1768715977012_90305535_1768716000855_72483504.jpg"}, {"title": [], "url": "https://aos-comment.amap.com/B0HRYZFHC8/comment/23c87051fd827e1c20127c30d28f9738_2048_2048_80.jpg"}], "building": [], "typecode": "080000", "shopinfo": "0", "poiweight": [], "adname": "道外区", "featured_reviews_remake": [], "tel": "0451-57636666", "id": "B0HRYZFHC8", "address": "先锋路2号", "space_num": [], "pname": "黑龙江省", "biz_type": [], "cityname": "哈尔滨市", "childtype": [], "atag": [], "name": "海豚堡水乐园", "location": "126.758141,45.773263", "shopid": [], "favorite_num": [], "featured_reviews": []}, {"parent": "B01C30LJJN", "distance": [], "keytag": "湿地", "importance": [], "biz_ext": {"cost": [], "opentime2": [], "level": [], "rating": "3.8", "open_time": [], "ticket_ordering": "0"}, "type": "风景名胜;公园广场;植物园", "photos": [{"provider": [], "title": [], "url": "http://store.is.autonavi.com/showpic/b8bd872e44c303e4d95d343ec14d92f1"}, {"provider": [], "title": [], "url": "http://store.is.autonavi.com/showpic/871d6997ebb7c8b4ee15ccf5fef6377c"}], "building": [], "typecode": "110103", "shopinfo": "2", "poiweight": [], "adname": "松北区", "featured_reviews_remake": [], "tel": [], "id": "B0FFIAEJRF", "address": "江湾路5000号金河湾湿地植物园(西北角)", "space_num": [], "pname": "黑龙江省", "biz_type": "tour", "cityname": "哈尔滨市", "childtype": "302", "atag": [], "name": "哈尔滨金河湾湿地植物园-管理区", "location": "126.494120,45.785443", "shopid": [], "favorite_num": [], "featured_reviews": []}, {"parent": "B0FFGDXA74", "distance": [], "keytag": "文物古迹", "importance": [], "biz_ext": {"cost": [], "opentime2": "周一至周日 10:15-22:00", "level": [], "rating": "4.1", "open_time": "10:15-22:00", "ticket_ordering": "0"}, "type": "风景名胜;风景名胜;风景名胜", "photos": [{"provider": [], "title": [], "url": "https://aos-comment.amap.com/B01C317JIC/comment/202603_11-14151_1773209724257_33841677.jpg"}, {"provider": [], "title": [], "url": "https://aos-comment.amap.com/B01C317JIC/comment/content_media_external_file_1000121616_ss__1752894190086_56443414.jpg"}, {"provider": [], "title": [], "url": "https://aos-comment.amap.com/B01C317JIC/comment/content_media_external_images_media_1000033444_ss__1766093807300_96189945.jpg"}], "building": [], "typecode": "110200", "shopinfo": "2", "poiweight": [], "adname": "道里区", "featured_reviews_remake": [], "tel": [], "id": "B01C317JIC", "address": "中央大街1号哈尔滨中央大街", "space_num": [], "pname": "黑龙江省", "biz_type": "tour", "cityname": "哈尔滨市", "childtype": "324", "atag": [], "name": "松浦洋行", "location": "126.618741,45.773647", "shopid": [], "favorite_num": [], "featured_reviews": []}, {"parent": [], "distance": [], "keytag": "游乐园", "importance": [], "biz_ext": {"cost": [], "opentime2": "周一至周五 09:00-21:00", "rating": "4.3", "open_time": "09:00-21:00"}, "type": "体育休闲服务;休闲场所;游乐场", "photos": [{"title": [], "url": "https://store.is.autonavi.com/showpic/f503774a915fe6e2e59416f7c13aa19a"}, {"title": [], "url": "https://aos-comment.amap.com/B0JD2Z9UB0/comment/37DE206A_223B_4B36_810B_4B2A6AAC0123_L0_001_1290_96_1748860419010_64816633.jpg"}, {"title": [], "url": "https://aos-comment.amap.com/B0JD2Z9UB0/comment/content_media_external_images_media_15861_ss__1759315251840_83099174.jpg"}], "building": [], "typecode": "080501", "shopinfo": "1", "poiweight": [], "adname": "道里区", "featured_reviews_remake": [], "tel": "15245011332", "id": "B0JD2Z9UB0", "address": "九站街1-3号", "space_num": [], "pname": "黑龙江省", "biz_type": [], "cityname": "哈尔滨市", "childtype": [], "atag": [], "name": "松花江沙滩嘉年华", "location": "126.606093,45.777660", "shopid": [], "favorite_num": [], "featured_reviews": []}, {"parent": [], "distance": [], "keytag": "特色景点", "importance": [], "biz_ext": {"cost": [], "opentime2": "5月 周一至周日 09:00-18:00；6月至8月 周一至周日 10:00-20:00", "level": [], "rating": "4.3", "open_time": [], "ticket_ordering": "0"}, "type": "风景名胜;风景名胜;风景名胜", "photos": [{"provider": [], "title": [], "url": "http://store.is.autonavi.com/showpic/b9c846fdbe250060f6a0bebda546b558"}, {"provider": [], "title": [], "url": "https://aos-comment.amap.com/B0FFG9204F/comment/6bc434979f714c629970a4443c74a504_2048_2048_80.jpg"}, {"provider": [], "title": [], "url": "https://aos-comment.amap.com/B0FFG9204F/comment/ecabbc032a9a25b2812023f32ca2ac16_2048_2048_80.jpg"}], "building": [], "typecode": "110200", "shopinfo": "2", "poiweight": [], "adname": "松北区", "featured_reviews_remake": [], "tel": "18745065857;18745068747", "id": "B0FFG9204F", "address": "对青山镇工农大街1号", "space_num": [], "pname": "黑龙江省", "biz_type": "tour", "cityname": "哈尔滨市", "childtype": [], "atag": [], "name": "哈尔滨新区花之语养息谷", "location": "126.349361,45.907659", "shopid": [], "favorite_num": [], "featured_reviews": []}, {"parent": "B01C30J40L", "distance": [], "keytag": "文物古迹", "importance": [], "biz_ext": {"cost": [], "opentime2": "周一至周日 09:00-16:30", "level": [], "rating": "4.5", "open_time": "09:00-16:30", "ticket_ordering": "0"}, "type": "风景名胜;风景名胜;风景名胜", "photos": [{"provider": [], "title": [], "url": "https://store.is.autonavi.com/showpic/0604d8fad841128753b8e8af3bd4dea7"}, {"provider": [], "title": [], "url": "https://store.is.autonavi.com/showpic/fc7cbdda327e5c83959d81eda5b5d99b"}, {"provider": [], "title": [], "url": "https://store.is.autonavi.com/showpic/24553279e768383b497198ffd0b56f1f"}], "building": [], "typecode": "110200", "shopinfo": "2", "poiweight": [], "adname": "平房区", "featured_reviews_remake": [], "tel": [], "id": "B01C317C67", "address": "新疆街派出所东侧", "space_num": [], "pname": "黑龙江省", "biz_type": "tour", "cityname": "哈尔滨市", "childtype": "301", "atag": [], "name": "侵华日军第731部队遗址第二保护区", "location": "126.633850,45.610616", "shopid": [], "favorite_num": [], "featured_reviews": []}], "total": 600}