{"ok": true, "pois": [{"parent": "B030505166", "pcode": "450000", "keytag": "自然风光", "type": "风景名胜;风景名胜相关;旅游景点", "photos": [{"provider": [], "title": [], "url": "https://aos-comment.amap.com/B03050W8JC/comment/e2da2dbbecb4cbcd6fde674adab623a1_2048_2048_80.jpg"}, {"provider": [], "title": [], "url": "https://aos-comment.amap.com/B03050W8JC/comment/content_media_external_file_45572_ss__1769364576648_46418467.jpg"}, {"provider": [], "title": [], "url": "https://aos-comment.amap.com/B03050W8JC/comment/content_media_external_file_1000005870_ss__1769325330889_29311056.jpg"}], "building": [], "typecode": "110000", "poiweight": [], "citycode": "0773", "adname": "七星区", "children": [], "featured_reviews_remake": [], "tel": "0773-5812174", "id": "B03050W8JC", "tag": [], "entr_location": [], "adcode": "450305", "pname": "广西壮族自治区", "biz_type": "tour", "cityname": "桂林市", "postcode": [], "business_area": "七星公园", "childtype": "301", "atag": [], "name": "乐水瀑布", "shopid": [], "favorite_num": [], "navi_poiid": [], "distance": [], "importance": [], "biz_ext": {"cost": [], "opentime2": "周一至周日 08:00-18:00 最晚进入17:30；停止售票:17:30 停止入场:17:30", "rating": "3.9", "open_time": "08:00-18:00", "ticket_ordering": "0"}, "recommend": "0", "discount_num": "0", "gridcode": "3710722412", "shopinfo": "2", "alias": [], "event": [], "indoor_map": "0", "email": [], "timestamp": "2026-06-14 03:59:50", "website": [], "address": "七星路1号七星景区内", "space_num": [], "match": "0", "indoor_data": {"cmsid": [], "truefloor": [], "cpid": [], "floor": []}, "exit_location": [], "location": "110.311076,25.271673", "groupbuy_num": "0", "featured_reviews": []}, {"parent": [], "pcode": "450000", "keytag": "景区", "type": "餐饮服务;餐饮相关场所;餐饮相关", "photos": [{"title": [], "url": "https://aos-comment.amap.com/B0G22UVD9U/comment/17E3638F_83E0_47AA_BB5B_F3DA063F0918_L0_001_1500_2000_1733458645896_72707998.jpg"}, {"title": [], "url": "https://aos-comment.amap.com/B0G22UVD9U/comment/917AD069_9F0E_4055_BD79_7705272D4F68_L0_001_2000_1500_1733458645895_31898738.jpg"}, {"title": [], "url": "https://aos-comment.amap.com/B0G22UVD9U/comment/3BD95088_7281_43F4_BCE9_8B19A12A9545_L0_001_2000_1500_1733458645895_03702575.jpg"}], "building": [], "typecode": "050000", "poiweight": [], "citycode": "0773", "adname": "雁山区", "children": [], "featured_reviews_remake": [], "tel": [], "id": "B0G22UVD9U", "tag": [], "entr_location": "110.322214,25.221376", "adcode": "450311", "pname": "广西壮族自治区", "biz_type": "diner", "cityname": "桂林市", "postcode": [], "business_area": [], "childtype": [], "atag": [], "name": "桂林记忆", "shopid": [], "favorite_num": [], "navi_poiid": [], "distance": [], "importance": [], "biz_ext": {"cost": [], "opentime2": [], "rating": "4.0", "open_time": [], "meal_ordering": "0"}, "recommend": "0", "discount_num": "0", "gridcode": "3710626512", "shopinfo": "0", "alias": [], "event": [], "indoor_map": "0", "email": [], "timestamp": "2026-04-29 13:45:06", "website": [], "address": "窑头生态采摘园东侧110米", "space_num": [], "match": "0", "indoor_data": {"cmsid": [], "truefloor": [], "cpid": [], "floor": []}, "exit_location": [], "location": "110.322613,25.221556", "groupbuy_num": "0", "featured_reviews": []}, {"parent": "B030506OF8", "pcode": "450000", "keytag": "景区", "type": "风景名胜;风景名胜相关;旅游景点", "photos": [], "building": [], "typecode": "110000", "poiweight": [], "citycode": "0773", "adname": "叠彩区", "children": [], "featured_reviews_remake": [], "tel": "0773-2231625", "id": "B0FFF35P2E", "tag": [], "entr_location": "110.298517,25.29157", "adcode": "450303", "pname": "广西壮族自治区", "biz_type": "tour", "cityname": "桂林市", "postcode": [], "business_area": "中山北路", "childtype": "301", "atag": [], "name": "木龙湖景区-东盟园", "shopid": [], "favorite_num": [], "navi_poiid": "G49F033019_105661", "distance": [], "importance": [], "biz_ext": {"cost": [], "opentime2": [], "rating": "3.4", "open_time": [], "ticket_ordering": "0"}, "recommend": "0", "discount_num": "0", "gridcode": "3710725400", "shopinfo": "2", "alias": [], "event": [], "indoor_map": "0", "email": [], "timestamp": "2026-04-02 12:02:32", "website": [], "address": "叠彩街道东镇路24号木龙湖(东北角)", "space_num": [], "match": "0", "indoor_data": {"cmsid": [], "truefloor": [], "cpid": [], "floor": []}, "exit_location": [], "location": "110.300985,25.292374", "groupbuy_num": "0", "featured_reviews": []}, {"parent": [], "pcode": "450000", "keytag": "5A景区", "type": "风景名胜;风景名胜;国家级景点", "photos": [{"provider": [], "title": [], "url": "http://store.is.autonavi.com/showpic/6f7c4694ee69fd6d5c2c3cd8f374c1a1"}, {"provider": [], "title": [], "url": "http://store.is.autonavi.com/showpic/1c2cd1169885aa439d2ae9ca8d2c706c"}, {"provider": [], "title": [], "url": "http://store.is.autonavi.com/showpic/8f608dfe92f7413d352205f03d16a843"}], "building": [], "typecode": "110202", "poiweight": [], "citycode": "0773", "adname": "灵川县", "children": [], "featured_reviews_remake": [], "tel": "0773-2881088;0773-8287688", "id": "B030507SVW", "tag": [], "entr_location": "110.431007,25.147581", "adcode": "450323", "pname": "广西壮族自治区", "biz_type": "tour", "cityname": "桂林市", "postcode": [], "business_area": [], "childtype": [], "atag": [], "name": "漓江景区", "shopid": [], "favorite_num": [], "navi_poiid": [], "distance": [], "importance": [], "biz_ext": {"cost": [], "opentime2": "周一至周日 00:00-24:00；开船时间:08:00-09:00", "rating": "4.6", "open_time": "00:00-24:00 08:00-09:00", "ticket_ordering": "0"}, "recommend": "0", "discount_num": "0", "gridcode": "3710537421", "shopinfo": "2", "alias": [], "event": [], "indoor_map": "0", "email": [], "timestamp": "2026-06-17 12:02:17", "website": [], "address": "磨盘山", "space_num": [], "match": "0", "indoor_data": {"cmsid": [], "truefloor": [], "cpid": [], "floor": []}, "exit_location": [], "location": "110.431685,25.147445", "groupbuy_num": "0", "featured_reviews": []}, {"parent": [], "pcode": "450000", "keytag": "景区", "type": "风景名胜;风景名胜相关;旅游景点", "photos": [{"provider": [], "title": "滨江景区", "url": "http://store.is.autonavi.com/showpic/742e4915ee96a3d7274219bcb621d9e7"}, {"provider": [], "title": [], "url": "https://aos-comment.amap.com/B0FFF0A6L3/comment/858EBF4E_95D9_4BCA_9308_BEBED1049B86_L0_001_2000_150_1750665544448_84216584.jpg"}, {"provider": [], "title": [], "url": "https://aos-comment.amap.com/B0FFF0A6L3/comment/content_media_external_file_126202_ss__1763684288368_92671722.jpg"}], "building": [], "typecode": "110000", "poiweight": [], "citycode": "0773", "adname": "秀峰区", "children": [], "featured_reviews_remake": [], "tel": "0773-8996303", "id": "B0FFF0A6L3", "tag": [], "entr_location": "110.303034,25.280530", "adcode": "450302", "pname": "广西壮族自治区", "biz_type": "tour", "cityname": "桂林市", "postcode": [], "business_area": "中心广场", "childtype": [], "atag": [], "name": "滨江景区", "shopid": [], "favorite_num": [], "navi_poiid": [], "distance": [], "importance": [], "biz_ext": {"cost": [], "opentime2": "周一至周日 07:00-18:30", "rating": "3.6", "open_time": "07:00-18:30", "ticket_ordering": "0"}, "recommend": "0", "discount_num": "0", "gridcode": "3710723420", "shopinfo": "2", "alias": [], "event": [], "indoor_map": "0", "email": [], "timestamp": "2026-06-12 15:39:14", "website": [], "address": "依仁路1-1附近", "space_num": [], "match": "0", "indoor_data": {"cmsid": [], "truefloor": [], "cpid": [], "floor": []}, "exit_location": [], "location": "110.302909,25.280561", "groupbuy_num": "0", "featured_reviews": []}, {"parent": [], "pcode": "450000", "keytag": "古镇古村", "type": "风景名胜;风景名胜;风景名胜", "photos": [{"provider": [], "title": [], "url": "http://store.is.autonavi.com/showpic/e0d6d9de93b0d64f70773191a1c1ef10"}, {"provider": [], "title": [], "url": "https://aos-comment.amap.com/B0FFG6RK2W/comment/content_media_external_file_1000062475_ss__1766807715981_63876411.jpg"}, {"provider": [], "title": [], "url": "https://store.is.autonavi.com/showpic/42ed8a10a08a78c30000001062604850?type=pic"}], "building": [], "typecode": "110200", "poiweight": [], "citycode": "0773", "adname": "灵川县", "children": [], "featured_reviews_remake": [], "tel": "0773-6350269", "id": "B0FFG6RK2W", "tag": [], "entr_location": "110.427029,25.183175", "adcode": "450323", "pname": "广西壮族自治区", "biz_type": "tour", "cityname": "桂林市", "postcode": [], "business_area": [], "childtype": [], "atag": [], "name": "大圩古镇", "shopid": [], "favorite_num": [], "navi_poiid": [], "distance": [], "importance": [], "biz_ext": {"cost": [], "opentime2": "周一至周日 00:00-24:00；具体营业状态以当天开放情况为准", "rating": "4.5", "open_time": "24小时营业", "ticket_ordering": "0"}, "recommend": "0", "discount_num": "0", "gridcode": "3710631420", "shopinfo": "2", "alias": [], "event": [], "indoor_map": "0", "email": [], "timestamp": "2026-06-17 08:08:07", "website": [], "address": "临江路250号漓江景区", "space_num": [], "match": "0", "indoor_data": {"cmsid": [], "truefloor": [], "cpid": [], "floor": []}, "exit_location": [], "location": "110.427751,25.181553", "groupbuy_num": "0", "featured_reviews": []}, {"parent": "B030506JEE", "pcode": "450000", "keytag": "景区", "type": "风景名胜;风景名胜相关;旅游景点", "photos": [{"provider": [], "title": [], "url": "https://aos-comment.amap.com/B0FFL6FKJ6/comment/E78ED27B_E28C_41AA_84FA_6C7FD35A262A_L0_001_2000_150_1745028476628_72076058.jpg"}, {"provider": [], "title": [], "url": "https://aos-comment.amap.com/B0FFL6FKJ6/comment/b8baeaff5bebafc043f509569ab4545f_2048_2048_80.jpg"}, {"provider": [], "title": [], "url": "https://aos-comment.amap.com/B0FFL6FKJ6/comment/01ac79d52d2ad1a650e26f11b106955c_2048_2048_80.jpg"}], "building": [], "typecode": "110000", "poiweight": [], "citycode": "0773", "adname": "叠彩区", "children": [], "featured_reviews_remake": [], "tel": "0773-2100660", "id": "B0FFL6FKJ6", "tag": [], "entr_location": "110.300742,25.291246", "adcode": "450303", "pname": "广西壮族自治区", "biz_type": "tour", "cityname": "桂林市", "postcode": [], "business_area": "中山北路", "childtype": "301", "atag": [], "name": "仙鹤洞", "shopid": [], "favorite_num": [], "navi_poiid": [], "distance": [], "importance": [], "biz_ext": {"cost": [], "opentime2": "周一至周日 00:00-24:00", "rating": "3.8", "open_time": "24小时营业", "ticket_ordering": "0"}, "recommend": "0", "discount_num": "0", "gridcode": "3710724420", "shopinfo": "2", "alias": [], "event": [], "indoor_map": "0", "email": [], "timestamp": "2026-06-13 22:41:12", "website": [], "address": "滨江路27号叠彩山内(西北角)", "space_num": [], "match": "0", "indoor_data": {"cmsid": [], "truefloor": [], "cpid": [], "floor": []}, "exit_location": [], "location": "110.300648,25.290678", "groupbuy_num": "0", "featured_reviews": []}, {"parent": [], "pcode": "450000", "keytag": "景区", "type": "风景名胜;风景名胜;风景名胜|政府机构及社会团体;政府机关;政府机关相关", "photos": [{"provider": [], "title": [], "url": "http://store.is.autonavi.com/showpic/24ee5d03f5767c82c1d23e55ba300003"}, {"provider": [], "title": [], "url": "http://store.is.autonavi.com/showpic/04720f951b62e34badafd001b88a54a7"}, {"provider": [], "title": [], "url": "http://store.is.autonavi.com/showpic/6d4cc2cb228c3f7c78572a1d7c77ee21"}], "building": [], "typecode": "110200|130100", "poiweight": [], "citycode": "0773", "adname": "叠彩区", "children": [], "featured_reviews_remake": [], "tel": "0773-2824344", "id": "B030507WR9", "tag": [], "entr_location": "110.303448,25.284487", "adcode": "450303", "pname": "广西壮族自治区", "biz_type": "tour", "cityname": "桂林市", "postcode": [], "business_area": [], "childtype": [], "atag": [], "name": "桂林市象山景区管理处", "shopid": [], "favorite_num": [], "navi_poiid": "G49F033019_16289", "distance": [], "importance": [], "biz_ext": {"cost": [], "opentime2": [], "rating": "3.7", "open_time": [], "ticket_ordering": "0"}, "recommend": "0", "discount_num": "0", "gridcode": "3710724400", "shopinfo": "2", "alias": "滨江景区管理处", "event": [], "indoor_map": "0", "email": [], "timestamp": "2026-05-12 19:25:39", "website": [], "address": "龙珠路2号", "space_num": [], "match": "0", "indoor_data": {"cmsid": [], "truefloor": [], "cpid": [], "floor": []}, "exit_location": [], "location": "110.303558,25.284535", "groupbuy_num": "0", "featured_reviews": []}, {"parent": "B0J0Y5P6IS", "pcode": "450000", "keytag": "景区", "type": "风景名胜;风景名胜;风景名胜|体育休闲服务;休闲场所;休闲场所", "photos": [{"provider": [], "title": [], "url": "http://store.is.autonavi.com/showpic/0e5364fd6e98ab69440feac9308e7b19"}, {"provider": [], "title": [], "url": "http://store.is.autonavi.com/showpic/a221806bf2d65085e12dc07fc1d08f03"}, {"provider": [], "title": [], "url": "http://store.is.autonavi.com/showpic/b54657addf924682b7b678155277186a"}], "building": [], "typecode": "110200|080500", "poiweight": [], "citycode": "0773", "adname": "雁山区", "children": [], "featured_reviews_remake": [], "tel": [], "id": "B0FFKCKP82", "tag": [], "entr_location": "110.311131,25.05829", "adcode": "450311", "pname": "广西壮族自治区", "biz_type": "tour", "cityname": "桂林市", "postcode": [], "business_area": [], "childtype": "301", "atag": [], "name": "桂林融创封神幻境演艺城", "shopid": [], "favorite_num": [], "navi_poiid": [], "distance": [], "importance": [], "biz_ext": {"cost": [], "opentime2": "全年 全天开放； 说明:6月桂林融创封神幻境演艺城运营时间 【海世界】 6月1日-6月30日 10:00-17:00 【欢乐部落】 06月01/06/07/13/14日（其他时间不开放） 11:00-17:00 6月19日-6月30日 11:00-17:00 【水世界】 6月19日-6月30日 11:00-18:00 【漓江后海商业街】 6月1日-6月30日 10:00-20:00 停止售票时间:闭园前1小时 停止入园时间:闭园前半小时 (水世界闭国前小时停止入园）", "rating": "4.5", "open_time": [], "ticket_ordering": "0"}, "recommend": "0", "discount_num": "0", "gridcode": "3710426500", "shopinfo": "2", "alias": "桂林融创国际旅游度假区", "event": [], "indoor_map": "0", "email": [], "timestamp": "2026-06-17 08:48:32", "website": [], "address": "大雁路398号", "space_num": [], "match": "0", "indoor_data": {"cmsid": [], "truefloor": [], "cpid": [], "floor": []}, "exit_location": [], "location": "110.314487,25.051683", "groupbuy_num": "0", "featured_reviews": []}, {"parent": "B030506W0W", "pcode": "450000", "keytag": "景区", "type": "风景名胜;风景名胜相关;旅游景点", "photos": [{"provider": [], "title": [], "url": "https://aos-comment.amap.com/B0G0K7TV9K/comment/IMG_20260104_160419_tem_1767513875610_83135583.jpg"}, {"provider": [], "title": [], "url": "https://aos-comment.amap.com/B0G0K7TV9K/comment/c29023181b9b0b8925e50d0604929aa9_2048_2048_80.jpg"}, {"provider": [], "title": [], "url": "https://aos-comment.amap.com/B0G0K7TV9K/comment/616f7914b9fdbaa847638b130ff0b18b_2048_2048_80.jpg"}], "building": [], "typecode": "110000", "poiweight": [], "citycode": "0773", "adname": "象山区", "children": [], "featured_reviews_remake": [], "tel": "0773-2582112", "id": "B0G0K7TV9K", "tag": [], "entr_location": [], "adcode": "450304", "pname": "广西壮族自治区", "biz_type": "tour", "cityname": "桂林市", "postcode": [], "business_area": [], "childtype": "301", "atag": [], "name": "象山景区-隐象亭", "shopid": [], "favorite_num": [], "navi_poiid": [], "distance": [], "importance": [], "biz_ext": {"cost": [], "opentime2": [], "rating": "3.3", "open_time": [], "ticket_ordering": "0"}, "recommend": "0", "discount_num": "0", "gridcode": "3710722301", "shopinfo": "2", "alias": [], "event": [], "indoor_map": "0", "email": [], "timestamp": "2026-06-12 06:07:22", "website": [], "address": "象鼻山景区内(西南角)", "space_num": [], "match": "0", "indoor_data": {"cmsid": [], "truefloor": [], "cpid": [], "floor": []}, "exit_location": [], "location": "110.295768,25.266899", "groupbuy_num": "0", "featured_reviews": []}, {"parent": "B0FFFFUA8P", "pcode": "450000", "keytag": "景区", "type": "风景名胜;风景名胜相关;旅游景点", "photos": [{"provider": [], "title": [], "url": "https://store.is.autonavi.com/showpic/daa690605caf2bd40000000663004991"}], "building": [], "typecode": "110000", "poiweight": [], "citycode": "0773", "adname": "象山区", "children": [], "featured_reviews_remake": [], "tel": [], "id": "B0HBBB0KN0", "tag": [], "entr_location": [], "adcode": "450304", "pname": "广西壮族自治区", "biz_type": "tour", "cityname": "桂林市", "postcode": [], "business_area": "中山南路", "childtype": "301", "atag": [], "name": "樱花亭", "shopid": [], "favorite_num": [], "navi_poiid": [], "distance": [], "importance": [], "biz_ext": {"cost": [], "opentime2": [], "rating": "3.3", "open_time": [], "ticket_ordering": "0"}, "recommend": "0", "discount_num": "0", "gridcode": "3710720300", "shopinfo": "2", "alias": [], "event": [], "indoor_map": "0", "email": [], "timestamp": "2026-01-20 13:06:32", "website": [], "address": "中山南路2号(近将军路)南溪山景区内", "space_num": [], "match": "0", "indoor_data": {"cmsid": [], "truefloor": [], "cpid": [], "floor": []}, "exit_location": [], "location": "110.288684,25.250730", "groupbuy_num": "0", "featured_reviews": []}, {"parent": "B030506W0W", "pcode": "450000", "keytag": "湖泊河流", "type": "风景名胜;风景名胜相关;旅游景点", "photos": [{"provider": [], "title": [], "url": "https://aos-comment.amap.com/B0FFLKIJT2/comment/542fa8f14b53483d73060bcf63a44f3d_2048_2048_80.jpg"}, {"provider": [], "title": [], "url": "https://aos-comment.amap.com/B0FFLKIJT2/comment/66596d1dc91d84956b2cf2b2dcdc30f3_2048_2048_80.jpg"}, {"provider": [], "title": [], "url": "https://aos-comment.amap.com/B0FFLKIJT2/comment/215f8536da156b02c4a202dd8063b2b1_2048_2048_80.jpg"}], "building": [], "typecode": "110000", "poiweight": [], "citycode": "0773", "adname": "象山区", "children": [], "featured_reviews_remake": [], "tel": "0773-2582112", "id": "B0FFLKIJT2", "tag": [], "entr_location": [], "adcode": "450304", "pname": "广西壮族自治区", "biz_type": "tour", "cityname": "桂林市", "postcode": [], "business_area": [], "childtype": "301", "atag": [], "name": "象鼻山景区-亲水区", "shopid": [], "favorite_num": [], "navi_poiid": [], "distance": [], "importance": [], "biz_ext": {"cost": [], "opentime2": [], "rating": "3.6", "open_time": [], "ticket_ordering": "0"}, "recommend": "0", "discount_num": "0", "gridcode": "3710722302", "shopinfo": "2", "alias": [], "event": [], "indoor_map": "0", "email": [], "timestamp": "2026-02-25 11:15:51", "website": [], "address": "民主路1号象鼻山景区内(北侧)", "space_num": [], "match": "0", "indoor_data": {"cmsid": [], "truefloor": [], "cpid": [], "floor": []}, "exit_location": [], "location": "110.297012,25.269403", "groupbuy_num": "0", "featured_reviews": []}, {"parent": "B0J0Y5P6IS", "pcode": "450000", "keytag": "4A景区", "type": "风景名胜;公园广场;公园", "photos": [{"provider": [], "title": [], "url": "https://aos-comment.amap.com/B030507TU3/comment/d312da0d3bb6f2be5f1a88cd6c1d53b3_2048_2048_80.jpg"}, {"provider": [], "title": [], "url": "https://store.is.autonavi.com/showpic/5a218527b30d21098fad46a45e89165a"}, {"provider": [], "title": [], "url": "https://aos-comment.amap.com/B030507TU3/comment/A4ABD4E7_AE6E_4FF6_A7C2_75D959104A4D_L0_001_1134_201_1763887372769_10464153.jpg"}], "building": [], "typecode": "110101", "poiweight": [], "citycode": "0773", "adname": "雁山区", "children": [], "featured_reviews_remake": [], "tel": "0773-3553878", "id": "B030507TU3", "tag": [], "entr_location": "110.309,25.077381", "adcode": "450311", "pname": "广西壮族自治区", "biz_type": "tour", "cityname": "桂林市", "postcode": [], "business_area": [], "childtype": "301", "atag": [], "name": "雁山园", "shopid": [], "favorite_num": [], "navi_poiid": "G49F036019_16", "distance": [], "importance": [], "biz_ext": {"cost": [], "opentime2": "周一至周日 09:00-17:00 最晚进入17:00；具体营业状态以当天开放情况为准", "rating": "4.4", "open_time": "09:00-17:00", "ticket_ordering": "0"}, "recommend": "0", "discount_num": "0", "gridcode": "3710429412", "shopinfo": "2", "alias": "广西省立师范专科学校旧址", "event": [], "indoor_map": "0", "email": [], "timestamp": "2026-06-17 08:53:00", "website": [], "address": "雁山镇良丰下村十号", "space_num": [], "match": "0", "indoor_data": {"cmsid": [], "truefloor": [], "cpid": [], "floor": []}, "exit_location": [], "location": "110.310202,25.077682", "groupbuy_num": "0", "featured_reviews": []}, {"parent": "B030501FFB", "pcode": "450000", "keytag": "景区", "type": "风景名胜;风景名胜相关;旅游景点", "photos": [{"provider": [], "title": [], "url": "https://aos-comment.amap.com/B0KRMLSVLI/comment/content_media_external_file_1000134830_ss__1771774954709_23080644.jpg"}, {"provider": [], "title": [], "url": "https://aos-comment.amap.com/comment/content_service__1771551190322_13773248_1771551482308_22841204.jpg"}, {"provider": [], "title": [], "url": "https://aos-comment.amap.com/B0KRMLSVLI/comment/content_media_external_file_1000048672_ss__1766102316393_43051926.jpg"}], "building": [], "typecode": "110000", "poiweight": [], "citycode": "0773", "adname": "叠彩区", "children": [], "featured_reviews_remake": [], "tel": [], "id": "B0KRMLSVLI", "tag": [], "entr_location": [], "adcode": "450303", "pname": "广西壮族自治区", "biz_type": "tour", "cityname": "桂林市", "postcode": [], "business_area": [], "childtype": "301", "atag": [], "name": "伏波山-山顶观景平台", "shopid": [], "favorite_num": [], "navi_poiid": [], "distance": [], "importance": [], "biz_ext": {"cost": [], "opentime2": "周一至周日 07:00-18:00", "rating": "3.7", "open_time": "07:00-18:00", "ticket_ordering": "0"}, "recommend": "0", "discount_num": "0", "gridcode": "3710724400", "shopinfo": "2", "alias": [], "event": [], "indoor_map": "0", "email": [], "timestamp": "2026-01-30 15:12:59", "website": [], "address": "滨江路27号伏波山风景区内", "space_num": [], "match": "0", "indoor_data": {"cmsid": [], "truefloor": [], "cpid": [], "floor": []}, "exit_location": [], "location": "110.303879,25.283751", "groupbuy_num": "0", "featured_reviews": []}, {"parent": "B0FFFAKZYV", "pcode": "450000", "keytag": "自然风光", "type": "风景名胜;风景名胜相关;旅游景点", "photos": [{"provider": [], "title": [], "url": "https://aos-comment.amap.com/B0G0KPSYX3/comment/20260310-b0f63a7c88305d716889bd2f-8cROHv9pxEYANh5CjLjVxt.jpg"}, {"provider": [], "title": [], "url": "https://aos-comment.amap.com/B0G0KPSYX3/comment/176544355355_1765443557764_25390734.jpg"}, {"provider": [], "title": [], "url": "https://aos-comment.amap.com/B0G0KPSYX3/comment/176544355655_1765443557765_86982332.jpg"}], "building": [], "typecode": "110000", "poiweight": [], "citycode": "0773", "adname": "象山区", "children": [], "featured_reviews_remake": [], "tel": "0773-2888802", "id": "B0G0KPSYX3", "tag": [], "entr_location": "110.288129,25.274191", "adcode": "450304", "pname": "广西壮族自治区", "biz_type": "tour", "cityname": "桂林市", "postcode": [], "business_area": [], "childtype": "301", "atag": [], "name": "芙蓉亭", "shopid": [], "favorite_num": [], "navi_poiid": [], "distance": [], "importance": [], "biz_ext": {"cost": [], "opentime2": "周一至周日 00:00-24:00", "rating": "3.7", "open_time": "24小时营业", "ticket_ordering": "0"}, "recommend": "0", "discount_num": "0", "gridcode": "3710722320", "shopinfo": "2", "alias": [], "event": [], "indoor_map": "0", "email": [], "timestamp": "2026-04-08 17:01:45", "website": [], "address": "滨江路2号两江四湖内", "space_num": [], "match": "0", "indoor_data": {"cmsid": [], "truefloor": [], "cpid": [], "floor": []}, "exit_location": [], "location": "110.287965,25.274334", "groupbuy_num": "0", "featured_reviews": []}, {"parent": "B0J0Y5P6IS", "pcode": "450000", "keytag": "生态公园", "type": "风景名胜;公园广场;公园", "photos": [{"provider": [], "title": [], "url": "http://store.is.autonavi.com/showpic/e3fa3d59a13a615c775fb87f03f844cd"}, {"provider": [], "title": [], "url": "http://store.is.autonavi.com/showpic/f6a66bee5577429acc19b3cfc42e6a10"}, {"provider": [], "title": [], "url": "http://store.is.autonavi.com/showpic/e6b3eed65873c03f603f5cf9026dd2a0"}], "building": [], "typecode": "110101", "poiweight": [], "citycode": "0773", "adname": "雁山区", "children": [], "featured_reviews_remake": [], "tel": "0773-3676200", "id": "B03050VOV0", "tag": [], "entr_location": "110.31226,25.058821", "adcode": "450311", "pname": "广西壮族自治区", "biz_type": "tour", "cityname": "桂林市", "postcode": [], "business_area": [], "childtype": "301", "atag": [], "name": "桂林园博园", "shopid": [], "favorite_num": [], "navi_poiid": "G49F036019_124", "distance": [], "importance": [], "biz_ext": {"cost": [], "opentime2": "周一至周日 09:00-18:00", "rating": "4.5", "open_time": "09:00-18:00", "ticket_ordering": "0"}, "recommend": "0", "discount_num": "0", "gridcode": "3710427510", "shopinfo": "2", "alias": "园博园", "event": [], "indoor_map": "0", "email": [], "timestamp": "2026-06-17 08:55:46", "website": [], "address": "雁山镇雁山街389号", "space_num": [], "match": "0", "indoor_data": {"cmsid": [], "truefloor": [], "cpid": [], "floor": []}, "exit_location": [], "location": "110.314488,25.063473", "groupbuy_num": "0", "featured_reviews": []}, {"parent": "B030509AJK", "pcode": "450000", "keytag": "景区", "type": "风景名胜;风景名胜相关;旅游景点", "photos": [], "building": [], "typecode": "110000", "poiweight": [], "citycode": "0773", "adname": "秀峰区", "children": [], "featured_reviews_remake": [], "tel": [], "id": "B0KUP55O1F", "tag": [], "entr_location": "110.270595,25.279971", "adcode": "450302", "pname": "广西壮族自治区", "biz_type": "tour", "cityname": "桂林市", "postcode": [], "business_area": "西山公园", "childtype": "301", "atag": [], "name": "刘三姐大观园-金蟾对歌台", "shopid": [], "favorite_num": [], "navi_poiid": [], "distance": [], "importance": [], "biz_ext": {"cost": [], "opentime2": [], "rating": "3.3", "open_time": [], "ticket_ordering": "0"}, "recommend": "0", "discount_num": "0", "gridcode": "3710723111", "shopinfo": "2", "alias": [], "event": [], "indoor_map": "0", "email": [], "timestamp": "2026-06-11 22:37:14", "website": [], "address": "桃花江路1号(近西山路)刘三姐大观园(东南角)", "space_num": [], "match": "0", "indoor_data": {"cmsid": [], "truefloor": [], "cpid": [], "floor": []}, "exit_location": [], "location": "110.270248,25.279918", "groupbuy_num": "0", "featured_reviews": []}, {"parent": "B030505166", "pcode": "450000", "keytag": "景区", "type": "风景名胜;风景名胜相关;旅游景点", "photos": [{"provider": [], "title": [], "url": "https://aos-comment.amap.com/B0FFK7YCP2/comment/content_media_external_file_45576_ss__1769364511793_02078157.jpg"}, {"provider": [], "title": [], "url": "https://aos-comment.amap.com/B0FFK7YCP2/comment/20260311-19d4e0349baa3b3ca808f9eb-2aN2GMAhsiZ6HDY2fsXdtg.jpg"}, {"provider": [], "title": [], "url": "https://aos-comment.amap.com/B0FFK7YCP2/comment/content_media_external_file_45582_ss__1769364511792_99750132.jpg"}], "building": [], "typecode": "110000", "poiweight": [], "citycode": "0773", "adname": "七星区", "children": [], "featured_reviews_remake": [], "tel": "0773-5812174", "id": "B0FFK7YCP2", "tag": [], "entr_location": [], "adcode": "450305", "pname": "广西壮族自治区", "biz_type": "tour", "cityname": "桂林市", "postcode": [], "business_area": "七星公园", "childtype": "301", "atag": [], "name": "猴趣", "shopid": [], "favorite_num": [], "navi_poiid": [], "distance": [], "importance": [], "biz_ext": {"cost": [], "opentime2": [], "rating": "3.6", "open_time": [], "ticket_ordering": "0"}, "recommend": "0", "discount_num": "0", "gridcode": "3710722412", "shopinfo": "2", "alias": [], "event": [], "indoor_map": "0", "email": [], "timestamp": "2026-06-11 12:22:39", "website": [], "address": "七星路1号七星公园内普陀山腹七星景区内(西侧)", "space_num": [], "match": "0", "indoor_data": {"cmsid": [], "truefloor": [], "cpid": [], "floor": []}, "exit_location": [], "location": "110.309884,25.271538", "groupbuy_num": "0", "featured_reviews": []}, {"parent": "B0305001D2", "pcode": "450000", "keytag": "景区", "type": "风景名胜;风景名胜;观景点", "photos": [{"provider": [], "title": [], "url": "https://aos-comment.amap.com/B0FFHCNKKI/comment/20260312-cce188ae18c2638fb73af636-5Zq8sq3VMyN6zBtw2ScfGO.jpg"}, {"provider": [], "title": [], "url": "https://store.is.autonavi.com/showpic/1a44300501e1432a0000000811230536?type=pic"}, {"provider": [], "title": [], "url": "https://store.is.autonavi.com/showpic/9327bfb33c09d93b0000000811248265?type=pic"}], "building": [], "typecode": "110209", "poiweight": [], "citycode": "0773", "adname": "七星区", "children": [], "featured_reviews_remake": [], "tel": [], "id": "B0FFHCNKKI", "tag": [], "entr_location": [], "adcode": "450305", "pname": "广西壮族自治区", "biz_type": "tour", "cityname": "桂林市", "postcode": [], "business_area": "穿山景区", "childtype": "301", "atag": [], "name": "穿山景区-观景台", "shopid": [], "favorite_num": [], "navi_poiid": [], "distance": [], "importance": [], "biz_ext": {"cost": [], "opentime2": [], "rating": "3.4", "open_time": [], "ticket_ordering": "0"}, "recommend": "0", "discount_num": "0", "gridcode": "3710720411", "shopinfo": "2", "alias": [], "event": [], "indoor_map": "0", "email": [], "timestamp": "2026-06-11 11:59:10", "website": [], "address": "穿山小街55号穿山景区内(北侧)", "space_num": [], "match": "0", "indoor_data": {"cmsid": [], "truefloor": [], "cpid": [], "floor": []}, "exit_location": [], "location": "110.304443,25.253437", "groupbuy_num": "0", "featured_reviews": []}, {"parent": [], "pcode": "450000", "keytag": "景区", "type": "风景名胜;风景名胜;风景名胜", "photos": [{"provider": [], "title": [], "url": "https://aos-comment.amap.com/B0FFIXEZTI/comment/9ac8009fcd31a6dabb9d9edae9983390_2048_2048_80.jpg"}, {"provider": [], "title": [], "url": "https://aos-comment.amap.com/B0FFIXEZTI/comment/0c87c9741a05a642b130668192c69752_2048_2048_80.jpg"}, {"provider": [], "title": [], "url": "https://aos-comment.amap.com/B0FFIXEZTI/comment/a874aa871b2894216ee4286f808c1355_2048_2048_80.jpg"}], "building": [], "typecode": "110200", "poiweight": [], "citycode": "0773", "adname": "临桂区", "children": [], "featured_reviews_remake": [], "tel": "13324837923", "id": "B0FFIXEZTI", "tag": [], "entr_location": "110.229126,25.047359", "adcode": "450312", "pname": "广西壮族自治区", "biz_type": "tour", "cityname": "桂林市", "postcode": [], "business_area": [], "childtype": [], "atag": [], "name": "会仙玻璃田", "shopid": [], "favorite_num": [], "navi_poiid": [], "distance": [], "importance": [], "biz_ext": {"cost": [], "opentime2": "周一至周日 08:00-18:00", "rating": "4.5", "open_time": "08:00-18:00", "ticket_ordering": "0"}, "recommend": "0", "discount_num": "0", "gridcode": "3710415820", "shopinfo": "2", "alias": [], "event": [], "indoor_map": "0", "email": [], "timestamp": "2026-06-17 08:12:19", "website": [], "address": "会仙镇同助村委沐宦头村3队8号", "space_num": [], "match": "0", "indoor_data": {"cmsid": [], "truefloor": [], "cpid": [], "floor": []}, "exit_location": [], "location": "110.229126,25.047258", "groupbuy_num": "0", "featured_reviews": []}, {"parent": [], "pcode": "450000", "keytag": "景区", "type": "风景名胜;风景名胜相关;旅游景点", "photos": [{"provider": [], "title": [], "url": "https://store.is.autonavi.com/showpic/3d9adb0fc8a5ee930000001108032544"}, {"provider": [], "title": [], "url": "https://store.is.autonavi.com/showpic/29f98d23a8d02f602656f17e7e1ab885"}], "building": [], "typecode": "110000", "poiweight": [], "citycode": "0773", "adname": "叠彩区", "children": [], "featured_reviews_remake": [], "tel": [], "id": "B0LBCCE9CM", "tag": [], "entr_location": "110.303403,25.331619", "adcode": "450303", "pname": "广西壮族自治区", "biz_type": "tour", "cityname": "桂林市", "postcode": [], "business_area": [], "childtype": [], "atag": [], "name": "漓江阳朔竹筏游船中心", "shopid": [], "favorite_num": [], "navi_poiid": [], "distance": [], "importance": [], "biz_ext": {"cost": [], "opentime2": [], "rating": "3.9", "open_time": [], "ticket_ordering": "0"}, "recommend": "0", "discount_num": "0", "gridcode": "3710729420", "shopinfo": "2", "alias": [], "event": [], "indoor_map": "0", "email": [], "timestamp": "2026-04-16 17:23:14", "website": [], "address": "盈丰路与广祥东巷交叉口东南20米", "space_num": [], "match": "0", "indoor_data": {"cmsid": [], "truefloor": [], "cpid": [], "floor": []}, "exit_location": [], "location": "110.303462,25.331626", "groupbuy_num": "0", "featured_reviews": []}, {"parent": "B030507HDH", "pcode": "450000", "keytag": "景区", "type": "风景名胜;风景名胜;国家级景点", "photos": [{"provider": [], "title": [], "url": "http://store.is.autonavi.com/showpic/d23b58dcc60243dd5007ecb780e2da9f"}, {"provider": [], "title": [], "url": "https://aos-comment.amap.com/B0FFFEE51T/comment/content_media_external_file_1000364178_ss__1747094663985_62285602.jpg"}, {"provider": [], "title": [], "url": "https://aos-comment.amap.com/B0FFFEE51T/comment/content_media_external_images_media_100016968_1730122538451_32207677.jpg"}], "building": [], "typecode": "110202", "poiweight": [], "citycode": "0773", "adname": "七星区", "children": [], "featured_reviews_remake": [], "tel": "0773-5893200;0773-5897276", "id": "B0FFFEE51T", "tag": [], "entr_location": "110.363802,25.291129", "adcode": "450305", "pname": "广西壮族自治区", "biz_type": "tour", "cityname": "桂林市", "postcode": [], "business_area": [], "childtype": "301", "atag": [], "name": "尧山靖江王陵景区", "shopid": [], "favorite_num": [], "navi_poiid": "G49F033019_849;38422", "distance": [], "importance": [], "biz_ext": {"cost": [], "opentime2": "周一至周日 09:00-16:30", "rating": "4.1", "open_time": "09:00-16:30", "ticket_ordering": "0"}, "recommend": "0", "discount_num": "0", "gridcode": "3710724920", "shopinfo": "2", "alias": "靖江王陵国家考古遗址公园", "event": [], "indoor_map": "0", "email": [], "timestamp": "2026-06-17 08:17:37", "website": [], "address": "朝阳乡靖江王陵博物馆东北侧60米", "space_num": [], "match": "0", "indoor_data": {"cmsid": [], "truefloor": [], "cpid": [], "floor": []}, "exit_location": [], "location": "110.365413,25.292258", "groupbuy_num": "0", "featured_reviews": []}, {"parent": "B0FFFCOLGJ", "pcode": "450000", "keytag": "景区", "type": "风景名胜;风景名胜相关;旅游景点", "photos": [{"provider": [], "title": [], "url": "https://aos-comment.amap.com/B0FFIZMY47/headerImg/171d7d6ca333e6ed59d9f3de95005ff3_2048_2048_80.jpg"}, {"provider": [], "title": [], "url": "https://aos-comment.amap.com/B0FFIZMY47/headerImg/38f83cf21e3e5c10d94587e7e70bed92_2048_2048_80.jpg"}, {"provider": [], "title": [], "url": "https://aos-comment.amap.com/B0FFIZMY47/headerImg/80f52cb0e7f3ee53056e4515924bcae6_2048_2048_80.jpg"}], "building": [], "typecode": "110000", "poiweight": [], "citycode": "0773", "adname": "秀峰区", "children": [], "featured_reviews_remake": [], "tel": "0773-2893193", "id": "B0FFIZMY47", "tag": [], "entr_location": [], "adcode": "450302", "pname": "广西壮族自治区", "biz_type": "tour", "cityname": "桂林市", "postcode": [], "business_area": "西山公园", "childtype": "301", "atag": [], "name": "龙头石林", "shopid": [], "favorite_num": [], "navi_poiid": [], "distance": [], "importance": [], "biz_ext": {"cost": [], "opentime2": [], "rating": "3.5", "open_time": [], "ticket_ordering": "0"}, "recommend": "0", "discount_num": "0", "gridcode": "3710724200", "shopinfo": "2", "alias": [], "event": [], "indoor_map": "0", "email": [], "timestamp": "2026-06-13 14:00:59", "website": [], "address": "西山路2号西山公园内(北侧)", "space_num": [], "match": "0", "indoor_data": {"cmsid": [], "truefloor": [], "cpid": [], "floor": []}, "exit_location": [], "location": "110.276557,25.284276", "groupbuy_num": "0", "featured_reviews": []}, {"parent": "B0FFM3N29M", "pcode": "450000", "keytag": "景区", "type": "风景名胜;风景名胜相关;旅游景点", "photos": [{"provider": [], "title": [], "url": "http://store.is.autonavi.com/showpic/d86894e780d2fa2e42b8c80cf72a9468"}], "building": [], "typecode": "110000", "poiweight": [], "citycode": "0773", "adname": "象山区", "children": [], "featured_reviews_remake": [], "tel": [], "id": "B0H61BMWPW", "tag": [], "entr_location": [], "adcode": "450304", "pname": "广西壮族自治区", "biz_type": "tour", "cityname": "桂林市", "postcode": [], "business_area": "联达商业广场", "childtype": "301", "atag": [], "name": "爱情风雨桥", "shopid": [], "favorite_num": [], "navi_poiid": [], "distance": [], "importance": [], "biz_ext": {"cost": [], "opentime2": [], "rating": "3.3", "open_time": [], "ticket_ordering": "0"}, "recommend": "0", "discount_num": "0", "gridcode": "3710720200", "shopinfo": "2", "alias": [], "event": [], "indoor_map": "0", "email": [], "timestamp": "2026-06-11 12:54:10", "website": [], "address": "珍稀植物园", "space_num": [], "match": "0", "indoor_data": {"cmsid": [], "truefloor": [], "cpid": [], "floor": []}, "exit_location": [], "location": "110.277871,25.252176", "groupbuy_num": "0", "featured_reviews": []}, {"parent": "B03050VG4W", "pcode": "450000", "keytag": "景区", "type": "风景名胜;风景名胜相关;旅游景点", "photos": [{"provider": [], "title": [], "url": "http://store.is.autonavi.com/showpic/16362d214d3fc37b19de52f5de9aa9f0"}, {"provider": [], "title": [], "url": "https://aos-comment.amap.com/B0FFFC35JF/comment/20260314-05730f178b3e0c23de58885b-8sjjRx2kocg7r7Oo9ESZci.jpg"}, {"provider": [], "title": [], "url": "http://store.is.autonavi.com/showpic/1fb61b27e595cc1c3d6b833eca42c299"}], "building": [], "typecode": "110000", "poiweight": [], "citycode": "0773", "adname": "秀峰区", "children": [], "featured_reviews_remake": [], "tel": "0773-2210889", "id": "B0FFFC35JF", "tag": [], "entr_location": "110.270972,25.30487", "adcode": "450302", "pname": "广西壮族自治区", "biz_type": "tour", "cityname": "桂林市", "postcode": [], "business_area": "桃花江", "childtype": "301", "atag": [], "name": "芦笛景区-芳莲池", "shopid": [], "favorite_num": [], "navi_poiid": [], "distance": [], "importance": [], "biz_ext": {"cost": [], "opentime2": "周一至周日 00:00-24:00", "rating": "3.5", "open_time": "24小时营业", "ticket_ordering": "0"}, "recommend": "0", "discount_num": "0", "gridcode": "3710726111", "shopinfo": "2", "alias": [], "event": [], "indoor_map": "0", "email": [], "timestamp": "2026-06-17 00:04:47", "website": [], "address": "甲山街道甲山街道芦笛路1号芦笛景区(西南角)", "space_num": [], "match": "0", "indoor_data": {"cmsid": [], "truefloor": [], "cpid": [], "floor": []}, "exit_location": [], "location": "110.269735,25.304063", "groupbuy_num": "0", "featured_reviews": []}], "total": 563}