{"ok": true, "pois": [{"parent": "B02180IYSA", "pcode": "370000", "keytag": "文物古迹", "type": "风景名胜;风景名胜相关;旅游景点", "photos": [{"provider": [], "title": [], "url": "http://store.is.autonavi.com/showpic/771410539d6b4a46b0c46d1a25188c46"}, {"provider": [], "title": [], "url": "https://store.is.autonavi.com/showpic/3914eb0dd2f58677748bbcdd49d231a3"}, {"provider": [], "title": [], "url": "https://store.is.autonavi.com/showpic/fb9c721862c465fdd36fc055455fccd3"}], "building": [], "typecode": "110000", "poiweight": [], "citycode": "0536", "adname": "奎文区", "children": [], "featured_reviews_remake": [], "tel": "0536-8233675", "id": "B0H64UIX2B", "tag": [], "entr_location": "119.134058,36.701585", "adcode": "370705", "pname": "山东省", "biz_type": "tour", "cityname": "潍坊市", "postcode": [], "business_area": "虞河", "childtype": "301", "atag": [], "name": "潍县·乐道院暨西方侨民集中营旧址", "shopid": [], "favorite_num": [], "navi_poiid": [], "distance": [], "importance": [], "biz_ext": {"cost": [], "opentime2": [], "rating": "4.1", "open_time": [], "ticket_ordering": "0"}, "recommend": "0", "discount_num": "0", "gridcode": "5519014002", "shopinfo": "2", "alias": [], "event": [], "indoor_map": "0", "email": [], "timestamp": "2026-05-17 21:10:13", "website": [], "address": "虞河路303号", "space_num": [], "match": "0", "indoor_data": {"cmsid": [], "truefloor": [], "cpid": [], "floor": []}, "exit_location": [], "location": "119.133788,36.701609", "groupbuy_num": "0", "featured_reviews": []}, {"parent": [], "pcode": "370000", "keytag": "湿地公园", "type": "风景名胜;风景名胜;国家级景点", "photos": [{"provider": [], "title": [], "url": "https://aos-comment.amap.com/B0FFG3F44Z/comment/content_media_external_file_1000112383_ss__1764315536181_44250229.jpg"}, {"provider": [], "title": [], "url": "https://aos-comment.amap.com/B0FFG3F44Z/comment/dcd3793d96385c313ef83a32c103ecd1_2048_2048_80.jpg"}, {"provider": [], "title": [], "url": "https://aos-comment.amap.com/B0FFG3F44Z/comment/9d79faa196d5b6132247faea0fa321be_2048_2048_80.jpg"}], "building": [], "typecode": "110202", "poiweight": [], "citycode": "0536", "adname": "寒亭区", "children": [], "featured_reviews_remake": [], "tel": [], "id": "B0FFG3F44Z", "tag": [], "entr_location": "119.118931,36.769017", "adcode": "370703", "pname": "山东省", "biz_type": "tour", "cityname": "潍坊市", "postcode": [], "business_area": [], "childtype": [], "atag": [], "name": "白浪河国家湿地公园", "shopid": [], "favorite_num": [], "navi_poiid": [], "distance": [], "importance": [], "biz_ext": {"cost": [], "opentime2": [], "rating": "4.6", "open_time": [], "ticket_ordering": "0"}, "recommend": "0", "discount_num": "0", "gridcode": "5519105902", "shopinfo": "2", "alias": [], "event": [], "indoor_map": "0", "email": [], "timestamp": "2026-05-19 11:20:18", "website": [], "address": "潍坊经济开发区民主街与鸢飞路西白浪河大桥西100米海泰地产东临白浪河", "space_num": [], "match": "0", "indoor_data": {"cmsid": [], "truefloor": [], "cpid": [], "floor": []}, "exit_location": [], "location": "119.122530,36.791794", "groupbuy_num": "0", "featured_reviews": []}, {"parent": [], "pcode": "370000", "keytag": "公园", "type": "风景名胜;公园广场;公园", "photos": [{"provider": [], "title": [], "url": "http://store.is.autonavi.com/showpic/cfae2e91adb30d7a67d935ed086d409f"}, {"provider": [], "title": [], "url": "https://aos-comment.amap.com/B0HGF44EV9/comment/content_media_external_file_100002073_1766398744763_81154214.jpg"}, {"provider": [], "title": [], "url": "https://store.is.autonavi.com/showpic/5ab017aa0d83b7370000002883680341?type=pic"}], "building": [], "typecode": "110101", "poiweight": [], "citycode": "0536", "adname": "寒亭区", "children": [], "featured_reviews_remake": [], "tel": [], "id": "B0HGF44EV9", "tag": [], "entr_location": "119.197528,36.749446", "adcode": "370703", "pname": "山东省", "biz_type": "tour", "cityname": "潍坊市", "postcode": [], "business_area": [], "childtype": [], "atag": [], "name": "寒亭体育公园", "shopid": [], "favorite_num": [], "navi_poiid": [], "distance": [], "importance": [], "biz_ext": {"cost": [], "opentime2": "周一至周日 00:00-24:00", "rating": "4.5", "open_time": "24小时营业", "ticket_ordering": "0"}, "recommend": "0", "discount_num": "0", "gridcode": "5519110502", "shopinfo": "2", "alias": "中房体育公园", "event": [], "indoor_map": "0", "email": [], "timestamp": "2026-05-19 11:31:49", "website": [], "address": "惠贤北路与祥亭街交叉口北150米", "space_num": [], "match": "0", "indoor_data": {"cmsid": [], "truefloor": [], "cpid": [], "floor": []}, "exit_location": [], "location": "119.198698,36.750676", "groupbuy_num": "0", "featured_reviews": []}, {"parent": [], "pcode": "370000", "keytag": "寺庙", "type": "风景名胜;风景名胜;寺庙道观", "photos": [{"provider": [], "title": [], "url": "https://store.is.autonavi.com/showpic/f7f05f057551d68dd7d854342a006602"}, {"provider": [], "title": [], "url": "https://store.is.autonavi.com/showpic/781254448deee1c416c1de2874031238"}, {"provider": [], "title": [], "url": "https://store.is.autonavi.com/showpic/fe79d4d17eb20099ff9da00ea43fbe7c"}], "building": [], "typecode": "110205", "poiweight": [], "citycode": "0536", "adname": "潍城区", "children": [], "featured_reviews_remake": [], "tel": [], "id": "B02181609U", "tag": [], "entr_location": "119.0974,36.704467", "adcode": "370702", "pname": "山东省", "biz_type": "tour", "cityname": "潍坊市", "postcode": [], "business_area": "中百", "childtype": [], "atag": [], "name": "五道庙", "shopid": [], "favorite_num": [], "navi_poiid": "J50F040041_20627", "distance": [], "importance": [], "biz_ext": {"cost": [], "opentime2": "周一至周日 00:00-24:00", "rating": "4.3", "open_time": "24小时营业", "ticket_ordering": "0"}, "recommend": "0", "discount_num": "0", "gridcode": "5519004712", "shopinfo": "2", "alias": [], "event": [], "indoor_map": "0", "email": [], "timestamp": "2026-02-01 19:54:41", "website": [], "address": "健康街爱国路", "space_num": [], "match": "0", "indoor_data": {"cmsid": [], "truefloor": [], "cpid": [], "floor": []}, "exit_location": [], "location": "119.096637,36.704588", "groupbuy_num": "0", "featured_reviews": []}, {"parent": [], "pcode": "370000", "keytag": "寺庙", "type": "风景名胜;风景名胜;寺庙道观", "photos": [{"provider": [], "title": "金泉寺", "url": "http://store.is.autonavi.com/showpic/b7718f7fbe791ee7cf678e1f1feabb08"}, {"provider": [], "title": [], "url": "http://store.is.autonavi.com/showpic/06d47df9f5373373b93b599ca88ecd22"}, {"provider": [], "title": [], "url": "http://store.is.autonavi.com/showpic/690e59a76b67654ce041eba288a8fe42"}], "building": [], "typecode": "110205", "poiweight": [], "citycode": "0536", "adname": "奎文区", "children": [], "featured_reviews_remake": [], "tel": "0536-2608220;0536-2608657", "id": "B0218017CC", "tag": [], "entr_location": "119.123352,36.659087", "adcode": "370705", "pname": "山东省", "biz_type": "tour", "cityname": "潍坊市", "postcode": [], "business_area": "金宝", "childtype": [], "atag": [], "name": "金泉寺", "shopid": [], "favorite_num": [], "navi_poiid": "J50F041041_44", "distance": [], "importance": [], "biz_ext": {"cost": [], "opentime2": "5月至9月 周一至周日 07:30-17:30；1月至4月,10月至12月 周一至周日 07:30-17:00", "rating": "4.4", "open_time": [], "ticket_ordering": "0"}, "recommend": "0", "discount_num": "0", "gridcode": "5419709902", "shopinfo": "2", "alias": [], "event": [], "indoor_map": "0", "email": [], "timestamp": "2026-06-17 09:55:11", "website": [], "address": "廿里堡街道潍州路519号(金宝乐园北邻)", "space_num": [], "match": "0", "indoor_data": {"cmsid": [], "truefloor": [], "cpid": [], "floor": []}, "exit_location": [], "location": "119.122367,36.660873", "groupbuy_num": "0", "featured_reviews": []}, {"parent": [], "pcode": "370000", "keytag": "4A景区", "type": "风景名胜;风景名胜;国家级景点|风景名胜;公园广场;公园", "photos": [{"provider": [], "title": [], "url": "http://store.is.autonavi.com/showpic/f87e2ac74fb3f75db58ad8b648996bbd"}, {"provider": [], "title": [], "url": "http://store.is.autonavi.com/showpic/9ff90f596b1044697e1b79222d0c9c70"}, {"provider": [], "title": [], "url": "http://store.is.autonavi.com/showpic/ddeb7acf3ed9e66eeb9e6c1844c3cc75"}], "building": [], "typecode": "110202|110101", "poiweight": [], "citycode": "0536", "adname": "安丘市", "children": [], "featured_reviews_remake": [], "tel": "0536-8025978", "id": "B0FFF9YNDI", "tag": [], "entr_location": "119.210476,36.527391", "adcode": "370784", "pname": "山东省", "biz_type": "tour", "cityname": "潍坊市", "postcode": [], "business_area": [], "childtype": [], "atag": [], "name": "世界风筝公园", "shopid": [], "favorite_num": [], "navi_poiid": [], "distance": [], "importance": [], "biz_ext": {"cost": [], "opentime2": "周一至周日 08:00-17:00", "rating": "4.5", "open_time": "08:00-17:00", "ticket_ordering": "0"}, "recommend": "0", "discount_num": "0", "gridcode": "5419614502", "shopinfo": "2", "alias": "齐鲁酒地|山东齐鲁酒地置业有限公司", "event": [], "indoor_map": "0", "email": [], "timestamp": "2026-06-17 08:46:06", "website": [], "address": "经济开发区新安路79号(新安路与风筝大街路口西北角)", "space_num": [], "match": "0", "indoor_data": {"cmsid": [], "truefloor": [], "cpid": [], "floor": []}, "exit_location": [], "location": "119.198749,36.534457", "groupbuy_num": "0", "featured_reviews": []}, {"parent": "B021800601", "pcode": "370000", "keytag": "城市公园", "type": "风景名胜;公园广场;公园", "photos": [{"provider": [], "title": [], "url": "https://store.is.autonavi.com/showpic/d7dd601f11947e3d0000002521316526?type=pic"}, {"provider": [], "title": [], "url": "http://store.is.autonavi.com/showpic/9fbb4ae9ef86800e19b134104196acea"}, {"provider": [], "title": [], "url": "https://aos-comment.amap.com/B0I2UU1PYC/comment/6e99b4c25e6eecdd4e4e83ccf7eb78e9_2048_2048_80.jpg"}], "building": [], "typecode": "110101", "poiweight": [], "citycode": "0536", "adname": "潍城区", "children": [], "featured_reviews_remake": [], "tel": [], "id": "B0I2UU1PYC", "tag": [], "entr_location": [], "adcode": "370702", "pname": "山东省", "biz_type": "tour", "cityname": "潍坊市", "postcode": [], "business_area": "青年路", "childtype": "301", "atag": [], "name": "归真园", "shopid": [], "favorite_num": [], "navi_poiid": [], "distance": [], "importance": [], "biz_ext": {"cost": [], "opentime2": "5月1日至9月30日周二至周日08:30-18:00(17:30停止入园,18:00闭园)10月1日至4月30日周二至周日08:30-17:30(17:00停止入园,17:30闭园)周一闭园(遇法定节假日,周一正常开园)", "rating": "4.4", "open_time": [], "ticket_ordering": "0"}, "recommend": "0", "discount_num": "0", "gridcode": "5519004801", "shopinfo": "2", "alias": [], "event": [], "indoor_map": "0", "email": [], "timestamp": "2026-05-19 11:31:49", "website": [], "address": "青年路人民公园", "space_num": [], "match": "0", "indoor_data": {"cmsid": [], "truefloor": [], "cpid": [], "floor": []}, "exit_location": [], "location": "119.107887,36.700992", "groupbuy_num": "0", "featured_reviews": []}, {"parent": "B02180JG07", "pcode": "370000", "keytag": "城市公园", "type": "风景名胜;公园广场;公园", "photos": [{"provider": [], "title": [], "url": "https://comment-oss-online.oss-cn-wulanchabu.aliyuncs.com/B0FFKTZ13R/headerImg/content_media_external_images_media_1055447_1653028138500_77286d68.jpg"}, {"provider": [], "title": [], "url": "https://aos-comment.amap.com/B0FFKTZ13R/comment/7a33478500593e417f84e6c7b246211a_2048_2048_80.jpg"}, {"provider": [], "title": [], "url": "https://aos-comment.amap.com/B0FFKTZ13R/comment/3b89d1306e6120877292f9bdde80f1f2_2048_2048_80.jpg"}], "building": [], "typecode": "110101", "poiweight": [], "citycode": "0536", "adname": "奎文区", "children": [], "featured_reviews_remake": [], "tel": [], "id": "B0FFKTZ13R", "tag": [], "entr_location": "119.229461,36.712584", "adcode": "370705", "pname": "山东省", "biz_type": "tour", "cityname": "潍坊市", "postcode": [], "business_area": [], "childtype": "301", "atag": [], "name": "浞河健康主题公园", "shopid": [], "favorite_num": [], "navi_poiid": [], "distance": [], "importance": [], "biz_ext": {"cost": [], "opentime2": "周一至周日 00:00-24:00", "rating": "4.3", "open_time": "24小时营业", "ticket_ordering": "0"}, "recommend": "0", "discount_num": "0", "gridcode": "5519015811", "shopinfo": "2", "alias": [], "event": [], "indoor_map": "0", "email": [], "timestamp": "2026-05-17 14:20:05", "website": [], "address": "健康东街与西浞河滨水休闲绿道交叉口西60米", "space_num": [], "match": "0", "indoor_data": {"cmsid": [], "truefloor": [], "cpid": [], "floor": []}, "exit_location": [], "location": "119.229288,36.712749", "groupbuy_num": "0", "featured_reviews": []}, {"parent": [], "pcode": "370000", "keytag": "广场", "type": "商务住宅;住宅区;住宅小区", "photos": [{"title": [], "url": "https://store.is.autonavi.com/showpic/bc95811742a6d2afedd1ebeb5891ee6a"}, {"title": [], "url": "https://store.is.autonavi.com/showpic/df521fc7771a30cac2ba3400f435e325"}, {"title": [], "url": "https://store.is.autonavi.com/showpic/5031868d4862ca0c7130207a580e1412"}], "building": [], "typecode": "120302", "poiweight": [], "citycode": "0536", "adname": "潍城区", "children": [], "featured_reviews_remake": [], "tel": [], "id": "B02180I6HS", "tag": [], "entr_location": "119.107142,36.713101", "adcode": "370702", "pname": "山东省", "biz_type": [], "cityname": "潍坊市", "postcode": [], "business_area": "和平路", "childtype": [], "atag": [], "name": "万兴隆广场", "shopid": [], "favorite_num": [], "navi_poiid": "J50F040041_62212", "distance": [], "importance": [], "biz_ext": {"cost": [], "opentime2": "周一至周日 10:00-21:30", "rating": "4.4", "open_time": "10:00-21:30"}, "recommend": "0", "discount_num": "0", "gridcode": "5519005811", "shopinfo": "0", "alias": [], "event": [], "indoor_map": "0", "email": [], "timestamp": "2026-06-17 10:02:24", "website": [], "address": "东风西街与向阳路交叉口东300米处", "space_num": [], "match": "0", "indoor_data": {"cmsid": [], "truefloor": [], "cpid": [], "floor": []}, "exit_location": [], "location": "119.107302,36.713760", "groupbuy_num": "0", "featured_reviews": []}, {"parent": [], "pcode": "370000", "keytag": "广场", "type": "风景名胜;公园广场;城市广场", "photos": [{"provider": [], "title": [], "url": "http://store.is.autonavi.com/showpic/cfb9a87ecc17782ce33403828ffe2028"}, {"provider": [], "title": [], "url": "http://store.is.autonavi.com/showpic/a967c81d581acb2db50cfa1a0de44ad5"}], "building": [], "typecode": "110105", "poiweight": [], "citycode": "0536", "adname": "潍城区", "children": [], "featured_reviews_remake": [], "tel": [], "id": "B0FFKFKT8T", "tag": [], "entr_location": "119.095484,36.713608", "adcode": "370702", "pname": "山东省", "biz_type": "tour", "cityname": "潍坊市", "postcode": [], "business_area": "中百", "childtype": [], "atag": [], "name": "月河社区新时代文明实践广场", "shopid": [], "favorite_num": [], "navi_poiid": [], "distance": [], "importance": [], "biz_ext": {"cost": [], "opentime2": "周一至周日 00:00-24:00", "rating": "3.7", "open_time": "24小时营业", "ticket_ordering": "0"}, "recommend": "0", "discount_num": "0", "gridcode": "5519005721", "shopinfo": "2", "alias": [], "event": [], "indoor_map": "0", "email": [], "timestamp": "2026-06-16 18:59:37", "website": [], "address": "东风西街与月河路交叉口西40米", "space_num": [], "match": "0", "indoor_data": {"cmsid": [], "truefloor": [], "cpid": [], "floor": []}, "exit_location": [], "location": "119.095682,36.713975", "groupbuy_num": "0", "featured_reviews": []}, {"parent": "B0H64UIX2B", "pcode": "370000", "keytag": "纪念馆", "type": "科教文化服务;博物馆;博物馆|风景名胜;风景名胜相关;旅游景点", "photos": [{"provider": [], "title": [], "url": "http://store.is.autonavi.com/showpic/d5e5aa2b35c3619e2dd271fa418560d7"}, {"provider": [], "title": [], "url": "http://store.is.autonavi.com/showpic/33ce723ded26a4c92cfdf61161b897f7"}, {"provider": [], "title": [], "url": "http://store.is.autonavi.com/showpic/fafe7623d3f6a79097912f47f399b0d0"}], "building": [], "typecode": "140100|110000", "poiweight": [], "citycode": "0536", "adname": "奎文区", "children": [], "featured_reviews_remake": [], "tel": "0536-8233675", "id": "B0FFGH6HIF", "tag": [], "entr_location": "119.134046,36.701462", "adcode": "370705", "pname": "山东省", "biz_type": [], "cityname": "潍坊市", "postcode": [], "business_area": "虞河", "childtype": "301", "atag": [], "name": "潍县西方侨民集中营旧址博物馆", "shopid": [], "favorite_num": [], "navi_poiid": [], "distance": [], "importance": [], "biz_ext": {"cost": [], "opentime2": [], "rating": "4.1", "open_time": [], "ticket_ordering": "0"}, "recommend": "0", "discount_num": "0", "gridcode": "5519014001", "shopinfo": "2", "alias": "潍县集中营纪念馆|乐道院潍县集中营博物馆", "event": [], "indoor_map": "0", "email": [], "timestamp": "2026-06-14 16:25:08", "website": [], "address": "虞河路人民医院北虞河景区内", "space_num": [], "match": "0", "indoor_data": {"cmsid": [], "truefloor": [], "cpid": [], "floor": []}, "exit_location": [], "location": "119.132024,36.702081", "groupbuy_num": "0", "featured_reviews": []}, {"parent": [], "pcode": "370000", "keytag": "革命纪念馆", "type": "风景名胜;公园广场;公园", "photos": [{"provider": [], "title": [], "url": "https://aos-comment.amap.com/B02180IYSA/comment/40c305c123915d3fbb3e3e3875bb7103_2048_2048_80.jpg"}, {"provider": [], "title": [], "url": "https://aos-comment.amap.com/B02180IYSA/comment/32a6fc30a66cde75bc6cf789e7f42beb_2048_2048_80.jpg"}, {"provider": [], "title": [], "url": "http://store.is.autonavi.com/showpic/96aa7b7d9db8dc8f8086f923e1d70072"}], "building": [], "typecode": "110101", "poiweight": [], "citycode": "0536", "adname": "奎文区", "children": [], "featured_reviews_remake": [], "tel": [], "id": "B02180IYSA", "tag": [], "entr_location": "119.134006,36.701479", "adcode": "370705", "pname": "山东省", "biz_type": "tour", "cityname": "潍坊市", "postcode": [], "business_area": "虞河", "childtype": [], "atag": [], "name": "河滨公园", "shopid": [], "favorite_num": [], "navi_poiid": "J50F040041_15769;8254", "distance": [], "importance": [], "biz_ext": {"cost": [], "opentime2": [], "rating": "4.5", "open_time": [], "ticket_ordering": "0"}, "recommend": "0", "discount_num": "0", "gridcode": "5519014011", "shopinfo": "2", "alias": [], "event": [], "indoor_map": "0", "email": [], "timestamp": "2026-05-19 11:36:45", "website": [], "address": "鸢飞路713号(近胜利东街)", "space_num": [], "match": "0", "indoor_data": {"cmsid": [], "truefloor": [], "cpid": [], "floor": []}, "exit_location": [], "location": "119.131690,36.702909", "groupbuy_num": "0", "featured_reviews": []}, {"parent": [], "pcode": "370000", "keytag": "3A景区", "type": "风景名胜;风景名胜;风景名胜", "photos": [{"provider": [], "title": [], "url": "https://store.is.autonavi.com/showpic/bd37deff7c425d9dad7c179ab6aa9ec4"}, {"provider": [], "title": [], "url": "https://aos-comment.amap.com/B02180IULK/comment/content_media_external_images_media_3937_1733508657386_40338416.jpg"}, {"provider": [], "title": [], "url": "https://store.is.autonavi.com/showpic/c00287f17d272b460000002901866550?type=pic"}], "building": [], "typecode": "110200", "poiweight": [], "citycode": "0536", "adname": "潍城区", "children": [], "featured_reviews_remake": [], "tel": "0536-8139889", "id": "B02180IULK", "tag": [], "entr_location": "119.010909,36.640881", "adcode": "370702", "pname": "山东省", "biz_type": "tour", "cityname": "潍坊市", "postcode": [], "business_area": [], "childtype": [], "atag": [], "name": "浮烟山", "shopid": [], "favorite_num": [], "navi_poiid": "J50F041041_294;812", "distance": [], "importance": [], "biz_ext": {"cost": [], "opentime2": "09:00-17:00(16:30截止售票)", "rating": "4.5", "open_time": "09:00-17:00", "ticket_ordering": "0"}, "recommend": "0", "discount_num": "0", "gridcode": "5419706022", "shopinfo": "2", "alias": "浮烟山休闲旅游度假区", "event": [], "indoor_map": "0", "email": [], "timestamp": "2026-06-17 00:00:34", "website": [], "address": "望留镇驻地", "space_num": [], "match": "0", "indoor_data": {"cmsid": [], "truefloor": [], "cpid": [], "floor": []}, "exit_location": [], "location": "119.010234,36.641121", "groupbuy_num": "0", "featured_reviews": []}, {"parent": [], "pcode": "370000", "keytag": "文物古迹", "type": "风景名胜;风景名胜;寺庙道观", "photos": [{"provider": [], "title": [], "url": "https://aos-comment.amap.com/B0KRZZDSNG/comment/content_media_external_images_media_1000070633_ss__1747559650805_50629582.jpg"}, {"provider": [], "title": [], "url": "https://aos-comment.amap.com/B0KRZZDSNG/comment/content_media_external_file_16_1768712528188_73326713.jpg"}, {"provider": [], "title": [], "url": "https://aos-comment.amap.com/B0KRZZDSNG/comment/content_media_external_images_media_1000070628_ss__1747559650808_51091303.jpg"}], "building": [], "typecode": "110205", "poiweight": [], "citycode": "0536", "adname": "潍城区", "children": [], "featured_reviews_remake": [], "tel": [], "id": "B0KRZZDSNG", "tag": [], "entr_location": "119.102759,36.714701", "adcode": "370702", "pname": "山东省", "biz_type": "tour", "cityname": "潍坊市", "postcode": [], "business_area": "和平路", "childtype": [], "atag": [], "name": "城隍庙", "shopid": [], "favorite_num": [], "navi_poiid": [], "distance": [], "importance": [], "biz_ext": {"cost": [], "opentime2": "周一至周日 07:00-18:30", "rating": "4.2", "open_time": "07:00-18:30", "ticket_ordering": "0"}, "recommend": "0", "discount_num": "0", "gridcode": "5519005820", "shopinfo": "2", "alias": [], "event": [], "indoor_map": "0", "email": [], "timestamp": "2026-05-20 13:13:08", "website": [], "address": "城隍庙街16号", "space_num": [], "match": "0", "indoor_data": {"cmsid": [], "truefloor": [], "cpid": [], "floor": []}, "exit_location": [], "location": "119.101658,36.715136", "groupbuy_num": "0", "featured_reviews": []}, {"parent": "B02181714Q", "pcode": "370000", "keytag": "动物园", "type": "体育休闲服务;休闲场所;休闲场所", "photos": [{"title": [], "url": "http://store.is.autonavi.com/showpic/f182bc1e1365f37616f437a6cecf92b9"}, {"title": [], "url": "http://store.is.autonavi.com/showpic/9259ff70417fe0e796dcce12522739dd"}, {"title": [], "url": "http://store.is.autonavi.com/showpic/3f8224f7eddb670c7fd404198fcc86a1"}], "building": [], "typecode": "080500", "poiweight": [], "citycode": "0536", "adname": "奎文区", "children": [], "featured_reviews_remake": [], "tel": "0536-3923939", "id": "B0FFJOZHIS", "tag": [], "entr_location": [], "adcode": "370705", "pname": "山东省", "biz_type": [], "cityname": "潍坊市", "postcode": [], "business_area": [], "childtype": "202", "atag": [], "name": "格林·噜咔奇幻动物王国", "shopid": [], "favorite_num": [], "navi_poiid": [], "distance": [], "importance": [], "biz_ext": {"cost": [], "opentime2": "周一至周日 09:30-18:00", "rating": "4.6", "open_time": "09:30-18:00"}, "recommend": "0", "discount_num": "0", "gridcode": "5519005802", "shopinfo": "0", "alias": [], "event": [], "indoor_map": "1", "email": [], "timestamp": "2026-06-17 08:45:37", "website": [], "address": "东风东街360号泰华城(潍坊店)泰华城假日广场1F层", "space_num": [], "match": "0", "indoor_data": {"cmsid": "CG0003460210100038", "truefloor": "1F", "cpid": "B0FFJF316A", "floor": "1"}, "exit_location": [], "location": "119.111525,36.710217", "groupbuy_num": "0", "featured_reviews": []}, {"parent": [], "pcode": "370000", "keytag": "人文景观", "type": "科教文化服务;博物馆;博物馆", "photos": [{"title": [], "url": "https://store.is.autonavi.com/showpic/68c5aa1f199c164c31a916ca7f13c954"}, {"title": [], "url": "https://aos-comment.amap.com/B0L395RS6O/comment/6FBB6E18_4692_4070_8767_11D1638F7DC9_L0_001_1500_200_1764864852723_70687588.jpg"}, {"title": [], "url": "https://aos-comment.amap.com/B0L395RS6O/comment/87AB4DE3_7726_4853_B089_E2CEAD2B0542_L0_001_1500_200_1769683043799_05220576.jpg"}], "building": [], "typecode": "140100", "poiweight": [], "citycode": "0536", "adname": "奎文区", "children": [], "featured_reviews_remake": [], "tel": "0536-5808050", "id": "B0L395RS6O", "tag": [], "entr_location": "119.133370,36.661657", "adcode": "370705", "pname": "山东省", "biz_type": [], "cityname": "潍坊市", "postcode": [], "business_area": [], "childtype": [], "atag": [], "name": "潍坊市非物质文化遗产馆", "shopid": [], "favorite_num": [], "navi_poiid": [], "distance": [], "importance": [], "biz_ext": {"cost": [], "opentime2": "10月1日至次年4月30日:周二至周日:09:00-16:30(16:00停止入场),周一正常闭馆(法定节假日除外)；5月1日至9月30日:周二至周日:09:00-17:00(16:30停止入场),周一正常闭馆(法定节假日除外)", "rating": "4.4", "open_time": []}, "recommend": "0", "discount_num": "0", "gridcode": "5419719011", "shopinfo": "0", "alias": [], "event": [], "indoor_map": "0", "email": [], "timestamp": "2026-06-14 18:43:24", "website": [], "address": "金宝街888号1532文化产业园内", "space_num": [], "match": "0", "indoor_data": {"cmsid": [], "truefloor": [], "cpid": [], "floor": []}, "exit_location": [], "location": "119.132771,36.661647", "groupbuy_num": "0", "featured_reviews": []}, {"parent": [], "pcode": "370000", "keytag": "广场", "type": "风景名胜;公园广场;城市广场", "photos": [{"provider": [], "title": [], "url": "https://aos-comment.amap.com/B0FFFE81NT/comment/fa5ffb0847fdc6774c3e919ad955f73c_2048_2048_80.jpg"}, {"provider": [], "title": [], "url": "https://aos-comment.amap.com/B0FFFE81NT/comment/5fbe73e25824d39d685ec7eb3811fbcd_2048_2048_80.jpg"}, {"provider": [], "title": [], "url": "http://store.is.autonavi.com/showpic/02ba228da2ae6a4b027f6e440c79459a"}], "building": [], "typecode": "110105", "poiweight": [], "citycode": "0536", "adname": "奎文区", "children": [], "featured_reviews_remake": [], "tel": [], "id": "B0FFFE81NT", "tag": [], "entr_location": "119.140743,36.686987", "adcode": "370705", "pname": "山东省", "biz_type": "tour", "cityname": "潍坊市", "postcode": [], "business_area": "虞河", "childtype": [], "atag": [], "name": "樱园文化广场", "shopid": [], "favorite_num": [], "navi_poiid": "J50F040042_23812", "distance": [], "importance": [], "biz_ext": {"cost": [], "opentime2": "周一至周日 00:00-24:00", "rating": "4.2", "open_time": "24小时营业", "ticket_ordering": "0"}, "recommend": "0", "discount_num": "0", "gridcode": "5519012110", "shopinfo": "2", "alias": [], "event": [], "indoor_map": "0", "email": [], "timestamp": "2026-04-03 13:46:29", "website": [], "address": "文化路91附近", "space_num": [], "match": "0", "indoor_data": {"cmsid": [], "truefloor": [], "cpid": [], "floor": []}, "exit_location": [], "location": "119.141415,36.687026", "groupbuy_num": "0", "featured_reviews": []}, {"parent": [], "pcode": "370000", "keytag": "湖泊河流", "type": "风景名胜;风景名胜相关;旅游景点", "photos": [{"provider": [], "title": [], "url": "https://store.is.autonavi.com/showpic/22f47a156c12c65b0000002337004544?type=pic"}, {"provider": [], "title": [], "url": "https://store.is.autonavi.com/showpic/68b07bdb873d61cd0000000718984927?type=pic"}, {"provider": [], "title": [], "url": "https://aos-comment.amap.com/B021815KJI/comment/content_media_external_file_1000104195_ss__1772343274767_10177803.jpg"}], "building": [], "typecode": "110000", "poiweight": [], "citycode": "0536", "adname": "奎文区", "children": [], "featured_reviews_remake": [], "tel": [], "id": "B021815KJI", "tag": [], "entr_location": "119.134151,36.711758", "adcode": "370705", "pname": "山东省", "biz_type": "tour", "cityname": "潍坊市", "postcode": [], "business_area": "虞河", "childtype": [], "atag": [], "name": "张面河景区", "shopid": [], "favorite_num": [], "navi_poiid": "J50F040042_7786", "distance": [], "importance": [], "biz_ext": {"cost": [], "opentime2": "周一至周日 00:00-24:00", "rating": "4.0", "open_time": "24小时营业", "ticket_ordering": "0"}, "recommend": "0", "discount_num": "0", "gridcode": "5519015012", "shopinfo": "2", "alias": [], "event": [], "indoor_map": "0", "email": [], "timestamp": "2026-05-19 11:32:10", "website": [], "address": "虞河路附近", "space_num": [], "match": "0", "indoor_data": {"cmsid": [], "truefloor": [], "cpid": [], "floor": []}, "exit_location": [], "location": "119.133537,36.711915", "groupbuy_num": "0", "featured_reviews": []}, {"parent": "B0FFFE5W9Y", "pcode": "370000", "keytag": "海滨浴场", "type": "风景名胜;风景名胜;海滩", "photos": [{"provider": [], "title": [], "url": "https://aos-comment.amap.com/B0FFMGAIUW/comment/8569D114_B078_4535_B636_1AA4A4704891_L0_001_2000_150_1770373486789_87483305.jpg"}, {"provider": [], "title": [], "url": "https://aos-comment.amap.com/B0FFMGAIUW/comment/CC4E2088_575D_4566_AF31_15C578936038_L0_001_1170_85_1755012710337_85826112.jpg"}, {"provider": [], "title": [], "url": "https://store.is.autonavi.com/showpic/9fc00971d717c3160000002402452484?type=pic"}], "building": [], "typecode": "110208", "poiweight": [], "citycode": "0536", "adname": "寒亭区", "children": [], "featured_reviews_remake": [], "tel": [], "id": "B0FFMGAIUW", "tag": [], "entr_location": "119.121343,36.790976", "adcode": "370703", "pname": "山东省", "biz_type": "tour", "cityname": "潍坊市", "postcode": [], "business_area": [], "childtype": "301", "atag": [], "name": "北辰沙滩", "shopid": [], "favorite_num": [], "navi_poiid": [], "distance": [], "importance": [], "biz_ext": {"cost": [], "opentime2": "周一至周日 08:00-19:00", "rating": "4.3", "open_time": "08:00-19:00", "ticket_ordering": "0"}, "recommend": "0", "discount_num": "0", "gridcode": "5519104902", "shopinfo": "2", "alias": [], "event": [], "indoor_map": "0", "email": [], "timestamp": "2026-06-04 23:33:18", "website": [], "address": "北辰绿洲湿地公园(东北角)", "space_num": [], "match": "0", "indoor_data": {"cmsid": [], "truefloor": [], "cpid": [], "floor": []}, "exit_location": [], "location": "119.121354,36.784720", "groupbuy_num": "0", "featured_reviews": []}, {"parent": [], "pcode": "370000", "keytag": "公园", "type": "风景名胜;公园广场;公园", "photos": [{"provider": [], "title": [], "url": "http://store.is.autonavi.com/showpic/1d92594b5a9d34baa1d2b78ec2337410"}, {"provider": [], "title": [], "url": "https://store.is.autonavi.com/showpic/a6560b825044f5d23d8a5129f8524055"}, {"provider": [], "title": [], "url": "https://store.is.autonavi.com/showpic/d5326e3159278614a06757b9c38b4247"}], "building": [], "typecode": "110101", "poiweight": [], "citycode": "0536", "adname": "奎文区", "children": [], "featured_reviews_remake": [], "tel": [], "id": "B0FFI1C14E", "tag": [], "entr_location": "119.165569,36.719413", "adcode": "370705", "pname": "山东省", "biz_type": "tour", "cityname": "潍坊市", "postcode": [], "business_area": "富华游乐园", "childtype": [], "atag": [], "name": "知微园", "shopid": [], "favorite_num": [], "navi_poiid": [], "distance": [], "importance": [], "biz_ext": {"cost": [], "opentime2": "周一至周日 00:00-24:00", "rating": "3.9", "open_time": "24小时营业", "ticket_ordering": "0"}, "recommend": "0", "discount_num": "0", "gridcode": "5519016300", "shopinfo": "2", "alias": [], "event": [], "indoor_map": "0", "email": [], "timestamp": "2026-06-11 21:02:16", "website": [], "address": "东方路2175号", "space_num": [], "match": "0", "indoor_data": {"cmsid": [], "truefloor": [], "cpid": [], "floor": []}, "exit_location": [], "location": "119.166307,36.718973", "groupbuy_num": "0", "featured_reviews": []}, {"parent": "B02180HZCE", "pcode": "370000", "keytag": "文物古迹", "type": "风景名胜;风景名胜;寺庙道观", "photos": [{"provider": [], "title": [], "url": "https://store.is.autonavi.com/showpic/a1a245998bd6ef750000002303758647?type=pic"}, {"provider": [], "title": [], "url": "https://aos-comment.amap.com/B02180JMXF/comment/content_media_external_file_1000036896_ss__1772179069688_48206148.jpg"}, {"provider": [], "title": [], "url": "https://aos-comment.amap.com/B02180JMXF/comment/content_media_external_file_1000036895_ss__1772179069685_18724635.jpg"}], "building": [], "typecode": "110205", "poiweight": [], "citycode": "0536", "adname": "潍城区", "children": [], "featured_reviews_remake": [], "tel": "0536-8131399", "id": "B02180JMXF", "tag": [], "entr_location": "119.009822,36.6528", "adcode": "370702", "pname": "山东省", "biz_type": "tour", "cityname": "潍坊市", "postcode": [], "business_area": [], "childtype": "301", "atag": [], "name": "浮烟山森林公园-洪福寺", "shopid": [], "favorite_num": [], "navi_poiid": "J50F041041_817", "distance": [], "importance": [], "biz_ext": {"cost": [], "opentime2": "周一至周日 07:30-17:00", "rating": "4.6", "open_time": "07:30-17:00", "ticket_ordering": "0"}, "recommend": "0", "discount_num": "0", "gridcode": "5419708012", "shopinfo": "2", "alias": [], "event": [], "indoor_map": "0", "email": [], "timestamp": "2026-06-17 00:02:55", "website": [], "address": [], "space_num": [], "match": "0", "indoor_data": {"cmsid": [], "truefloor": [], "cpid": [], "floor": []}, "exit_location": [], "location": "119.008688,36.652882", "groupbuy_num": "0", "featured_reviews": []}, {"parent": [], "pcode": "370000", "keytag": "公园", "type": "风景名胜;风景名胜相关;旅游景点", "photos": [{"provider": [], "title": [], "url": "https://store.is.autonavi.com/showpic/4de6a99ac7e355380000002318138731?type=pic"}, {"provider": [], "title": [], "url": "https://store.is.autonavi.com/showpic/8d2c937024a072f60000002399096569?type=pic"}, {"provider": [], "title": [], "url": "https://store.is.autonavi.com/showpic/d03782e7181a810c0000002399122237?type=pic"}], "building": [], "typecode": "110000", "poiweight": [], "citycode": "0536", "adname": "潍城区", "children": [], "featured_reviews_remake": [], "tel": "16628541402", "id": "B0L3JUDFDG", "tag": [], "entr_location": [], "adcode": "370702", "pname": "山东省", "biz_type": "tour", "cityname": "潍坊市", "postcode": [], "business_area": [], "childtype": [], "atag": [], "name": "亚美部落美食公园", "shopid": [], "favorite_num": [], "navi_poiid": [], "distance": [], "importance": [], "biz_ext": {"cost": [], "opentime2": "周一至周日 00:00-24:00", "rating": "4.2", "open_time": "24小时营业", "ticket_ordering": "0"}, "recommend": "0", "discount_num": "0", "gridcode": "5519007512", "shopinfo": "2", "alias": [], "event": [], "indoor_map": "0", "email": [], "timestamp": "2026-06-15 16:48:28", "website": [], "address": "清平路与北宫西街交叉口东北180米", "space_num": [], "match": "0", "indoor_data": {"cmsid": [], "truefloor": [], "cpid": [], "floor": []}, "exit_location": [], "location": "119.074375,36.727925", "groupbuy_num": "0", "featured_reviews": []}, {"parent": [], "pcode": "370000", "keytag": "游乐园", "type": "体育休闲服务;休闲场所;游乐场|体育休闲服务;休闲场所;水上活动中心", "photos": [{"title": [], "url": "http://store.is.autonavi.com/showpic/6dc10f8b5220cef672330a3d65956df8"}, {"title": [], "url": "http://store.is.autonavi.com/showpic/8a9d7646fbf847d89f5153e423a63ae3"}, {"title": [], "url": "http://store.is.autonavi.com/showpic/c80c742cc074471eeaf1152bc3bbb308"}], "building": [], "typecode": "080501|080505", "poiweight": [], "citycode": "0536", "adname": "潍城区", "children": [], "featured_reviews_remake": [], "tel": "0536-2256566", "id": "B0FFICNER1", "tag": [], "entr_location": "119.071541,36.73222", "adcode": "370702", "pname": "山东省", "biz_type": [], "cityname": "潍坊市", "postcode": [], "business_area": [], "childtype": [], "atag": [], "name": "海上明珠乐园", "shopid": [], "favorite_num": [], "navi_poiid": [], "distance": [], "importance": [], "biz_ext": {"cost": [], "opentime2": "04-24至06-30 周一至周日 09:30-17:30", "rating": "4.6", "open_time": "09:30-17:30"}, "recommend": "0", "discount_num": "0", "gridcode": "5519008501", "shopinfo": "0", "alias": [], "event": [], "indoor_map": "0", "email": [], "timestamp": "2026-06-17 09:55:53", "website": [], "address": "清平路与卧龙西街交汇处西3888号1号楼202", "space_num": [], "match": "0", "indoor_data": {"cmsid": [], "truefloor": [], "cpid": [], "floor": []}, "exit_location": [], "location": "119.069467,36.733426", "groupbuy_num": "0", "featured_reviews": []}, {"parent": [], "pcode": "370000", "keytag": "自然风光", "type": "风景名胜;风景名胜相关;旅游景点", "photos": [{"provider": [], "title": [], "url": "https://aos-comment.amap.com/B0FFHWOTS7/comment/content_media_external_file_100008013_1766237785767_43325578.jpg"}, {"provider": [], "title": [], "url": "http://store.is.autonavi.com/showpic/bce6d86d6634fd7c635acc847892e093"}, {"provider": [], "title": [], "url": "https://store.is.autonavi.com/showpic/f5451d01127078bb0000002883422639?type=pic"}], "building": [], "typecode": "110000", "poiweight": [], "citycode": "0536", "adname": "坊子区", "children": [], "featured_reviews_remake": [], "tel": [], "id": "B0FFHWOTS7", "tag": [], "entr_location": "119.152577,36.637185", "adcode": "370704", "pname": "山东省", "biz_type": "tour", "cityname": "潍坊市", "postcode": [], "business_area": [], "childtype": [], "atag": [], "name": "状元湖", "shopid": [], "favorite_num": [], "navi_poiid": [], "distance": [], "importance": [], "biz_ext": {"cost": [], "opentime2": "周一至周日 00:00-24:00", "rating": "4.1", "open_time": "24小时营业", "ticket_ordering": "0"}, "recommend": "0", "discount_num": "0", "gridcode": "5419716220", "shopinfo": "2", "alias": [], "event": [], "indoor_map": "0", "email": [], "timestamp": "2026-04-18 09:04:27", "website": [], "address": "双羊街与泰和路交叉口西南460米", "space_num": [], "match": "0", "indoor_data": {"cmsid": [], "truefloor": [], "cpid": [], "floor": []}, "exit_location": [], "location": "119.151850,36.641620", "groupbuy_num": "0", "featured_reviews": []}, {"parent": "B02180JXVB", "pcode": "370000", "keytag": "植物园", "type": "风景名胜;公园广场;植物园", "photos": [{"provider": [], "title": [], "url": "https://aos-comment.amap.com/B0FFFEBLOZ/comment/19999dc0f8a5e965b9a44f46258761bd_2048_2048_80.jpg"}, {"provider": [], "title": [], "url": "https://aos-comment.amap.com/B0FFFEBLOZ/comment/6866ac4c2843c6f99b864ad1d5e39c67_2048_2048_80.jpg"}, {"provider": [], "title": [], "url": "https://aos-comment.amap.com/B0FFFEBLOZ/comment/819cf8f68e38e0eab227b04ffee9a8d9_2048_2048_80.jpg"}], "building": [], "typecode": "110103", "poiweight": [], "citycode": "0536", "adname": "奎文区", "children": [], "featured_reviews_remake": [], "tel": "0536-8890635", "id": "B0FFFEBLOZ", "tag": [], "entr_location": "119.159004,36.681740", "adcode": "370705", "pname": "山东省", "biz_type": "tour", "cityname": "潍坊市", "postcode": [], "business_area": [], "childtype": "301", "atag": [], "name": "潍坊植物园-牡丹园", "shopid": [], "favorite_num": [], "navi_poiid": "J50F040042_23966", "distance": [], "importance": [], "biz_ext": {"cost": [], "opentime2": "周一至周日 00:00-24:00", "rating": "3.8", "open_time": "24小时营业", "ticket_ordering": "0"}, "recommend": "0", "discount_num": "0", "gridcode": "5519011220", "shopinfo": "2", "alias": [], "event": [], "indoor_map": "0", "email": [], "timestamp": "2026-05-19 11:21:10", "website": [], "address": "梨园路潍坊植物园(西北角)", "space_num": [], "match": "0", "indoor_data": {"cmsid": [], "truefloor": [], "cpid": [], "floor": []}, "exit_location": [], "location": "119.153523,36.682683", "groupbuy_num": "0", "featured_reviews": []}], "total": 600}